{
 "data_as_of": "2026-06-24",
 "figures": {
  "cas_confirmes_en_isolement": 205,
  "cas_suspects_en_isolement": 180,
  "contact_followup_rate_pct": 79.2,
  "country_scope_confirmed_deaths": 306,
  "country_scope_confirmed_deaths_uganda_anchor": 2,
  "country_scope_confirmed_total": 1175,
  "country_scope_confirmed_uganda_anchor": 20,
  "country_scope_recovered_total": 149,
  "country_scope_recovered_uganda_anchor": 11,
  "cumul_cas_confirmes_drc": 1155,
  "cumul_deces_parmi_confirmes_drc": 304,
  "gueris": 138,
  "new_confirmed_24h": 37,
  "new_confirmed_deaths_24h": 5,
  "new_affected_health_zones": [],
  "not_published_fields": [
   "cas_suspects_en_cours_investigation",
   "suspected_active_total",
   "deaths_suspected_drc_cumulative",
   "pcr_access_points_named_current_cycle",
   "south_kivu_lab_backlog_current_cycle",
   "health_worker_infection_zone_breakdown"
  ],
  "health_zone_table": {
   "basis": "SitRep41 Table 2 (24 June 2026) visually reviewed against the INSP PDF and reconciled to Table 1/province totals 1155/304. No new affected health zone is reported; the affected-zone count remains 34/104. The table carries 17 Ituri cases in zones not yet identified; these remain an unventilated residual and are not distributed to named health zones. PDF sha256 656822f7d31650f2b46c602c7decd620fd7ebb4b9f92d5e0bde730b8184182c2.",
   "date": "2026-06-24",
   "province_totals": [
    {
     "province": "Ituri",
     "confirmed": 1054,
     "confirmed_deaths": 250,
     "cfr_percent": 23.7,
     "health_zones_touched": "22/36",
     "new_confirmed_24h": 34
    },
    {
     "province": "Nord-Kivu",
     "confirmed": 98,
     "confirmed_deaths": 53,
     "cfr_percent": 54.1,
     "health_zones_touched": "11/34",
     "new_confirmed_24h": 3
    },
    {
     "province": "Sud-Kivu",
     "confirmed": 3,
     "confirmed_deaths": 1,
     "cfr_percent": 33.3,
     "health_zones_touched": "1/34",
     "new_confirmed_24h": 0
    }
   ],
   "reconciliation": {
    "named_zone_confirmed_deaths": 304,
    "named_zone_confirmed_sum": 1138,
    "national_confirmed_deaths_total": 304,
    "national_confirmed_total": 1155,
    "note": "Rows promoted here reconcile to official province/national totals: 1138 named confirmed cases plus 17 Ituri cases awaiting ventilation; all 304 confirmed deaths are named-zone attributed. The residual row is retained as unventilated context and excluded from mappable named-zone attribution.",
    "unventilated_ituri_confirmed": 17,
    "unventilated_ituri_confirmed_deaths": 0
   },
   "rows": [
    {
     "cfr_percent": 19.1,
     "confirmed": 314,
     "confirmed_deaths": 60,
     "province": "Ituri",
     "zone": "Bunia"
    },
    {
     "cfr_percent": 16.9,
     "confirmed": 237,
     "confirmed_deaths": 40,
     "province": "Ituri",
     "zone": "Rwampara"
    },
    {
     "cfr_percent": 42.9,
     "confirmed": 245,
     "confirmed_deaths": 105,
     "province": "Ituri",
     "zone": "Mongbwalu"
    },
    {
     "cfr_percent": 11.0,
     "confirmed": 91,
     "confirmed_deaths": 10,
     "province": "Ituri",
     "zone": "Nyankunde"
    },
    {
     "cfr_percent": 20.0,
     "confirmed": 30,
     "confirmed_deaths": 6,
     "province": "Ituri",
     "zone": "Nizi"
    },
    {
     "cfr_percent": 23.1,
     "confirmed": 26,
     "confirmed_deaths": 6,
     "province": "Ituri",
     "zone": "Lita"
    },
    {
     "cfr_percent": 23.1,
     "confirmed": 13,
     "confirmed_deaths": 3,
     "province": "Ituri",
     "zone": "Komanda"
    },
    {
     "cfr_percent": 14.3,
     "confirmed": 14,
     "confirmed_deaths": 2,
     "province": "Ituri",
     "zone": "Bambu"
    },
    {
     "cfr_percent": 11.1,
     "confirmed": 9,
     "confirmed_deaths": 1,
     "province": "Ituri",
     "zone": "Kilo"
    },
    {
     "cfr_percent": 47.1,
     "confirmed": 17,
     "confirmed_deaths": 8,
     "province": "Ituri",
     "zone": "Mangala"
    },
    {
     "cfr_percent": 0.0,
     "confirmed": 9,
     "confirmed_deaths": 0,
     "province": "Ituri",
     "zone": "Tchomia"
    },
    {
     "cfr_percent": 0.0,
     "confirmed": 4,
     "confirmed_deaths": 0,
     "province": "Ituri",
     "zone": "Damas"
    },
    {
     "cfr_percent": 33.3,
     "confirmed": 6,
     "confirmed_deaths": 2,
     "province": "Ituri",
     "zone": "Aungba"
    },
    {
     "cfr_percent": 0.0,
     "confirmed": 3,
     "confirmed_deaths": 0,
     "province": "Ituri",
     "zone": "Rimba"
    },
    {
     "cfr_percent": 33.3,
     "confirmed": 3,
     "confirmed_deaths": 1,
     "province": "Ituri",
     "zone": "Aru"
    },
    {
     "cfr_percent": 50.0,
     "confirmed": 2,
     "confirmed_deaths": 1,
     "province": "Ituri",
     "zone": "Mambasa"
    },
    {
     "cfr_percent": 0.0,
     "confirmed": 5,
     "confirmed_deaths": 0,
     "province": "Ituri",
     "zone": "Logo"
    },
    {
     "cfr_percent": 100.0,
     "confirmed": 1,
     "confirmed_deaths": 1,
     "province": "Ituri",
     "zone": "Drodro"
    },
    {
     "cfr_percent": 0.0,
     "confirmed": 1,
     "confirmed_deaths": 0,
     "province": "Ituri",
     "zone": "Gety"
    },
    {
     "cfr_percent": 100.0,
     "confirmed": 1,
     "confirmed_deaths": 1,
     "province": "Ituri",
     "zone": "Kambala"
    },
    {
     "cfr_percent": 60.0,
     "confirmed": 5,
     "confirmed_deaths": 3,
     "province": "Ituri",
     "zone": "Nia-Nia"
    },
    {
     "cfr_percent": 0.0,
     "confirmed": 1,
     "confirmed_deaths": 0,
     "province": "Ituri",
     "zone": "Fataki"
    },
    {
     "cfr_percent": 0.0,
     "confirmed": 17,
     "confirmed_deaths": 0,
     "province": "Ituri",
     "zone": "Autres ZS (donnees non ventilees)"
    },
    {
     "cfr_percent": 41.9,
     "confirmed": 31,
     "confirmed_deaths": 13,
     "province": "Nord-Kivu",
     "zone": "Butembo"
    },
    {
     "cfr_percent": 60.6,
     "confirmed": 33,
     "confirmed_deaths": 20,
     "province": "Nord-Kivu",
     "zone": "Katwa"
    },
    {
     "cfr_percent": 60.0,
     "confirmed": 20,
     "confirmed_deaths": 12,
     "province": "Nord-Kivu",
     "zone": "Beni"
    },
    {
     "cfr_percent": 66.7,
     "confirmed": 3,
     "confirmed_deaths": 2,
     "province": "Nord-Kivu",
     "zone": "Oicha"
    },
    {
     "cfr_percent": 50.0,
     "confirmed": 2,
     "confirmed_deaths": 1,
     "province": "Nord-Kivu",
     "zone": "Kalunguta"
    },
    {
     "cfr_percent": 66.7,
     "confirmed": 3,
     "confirmed_deaths": 2,
     "province": "Nord-Kivu",
     "zone": "Kyondo"
    },
    {
     "cfr_percent": 0.0,
     "confirmed": 1,
     "confirmed_deaths": 0,
     "province": "Nord-Kivu",
     "zone": "Goma"
    },
    {
     "cfr_percent": 0.0,
     "confirmed": 1,
     "confirmed_deaths": 0,
     "province": "Nord-Kivu",
     "zone": "Masereka"
    },
    {
     "cfr_percent": 100.0,
     "confirmed": 1,
     "confirmed_deaths": 1,
     "province": "Nord-Kivu",
     "zone": "Vuhovi"
    },
    {
     "cfr_percent": 0.0,
     "confirmed": 1,
     "confirmed_deaths": 0,
     "province": "Nord-Kivu",
     "zone": "Mabalako"
    },
    {
     "cfr_percent": 100.0,
     "confirmed": 2,
     "confirmed_deaths": 2,
     "province": "Nord-Kivu",
     "zone": "Musienene"
    },
    {
     "cfr_percent": 33.3,
     "confirmed": 3,
     "confirmed_deaths": 1,
     "province": "Sud-Kivu",
     "zone": "Miti-Murhesa"
    }
   ]
  },
  "lab_indicators_24h": {
   "nord_kivu_lab_reported": true,
   "note": "National aggregate from SitRep41 section 4.3: Ituri 134 collected/analyzed / 34 positive; Nord-Kivu 117 received, 97 analyzed / 3 positive (20 still under analysis); Sud-Kivu 6 collected/analyzed / 0 positive. Positivity uses 37 positives over 237 analyzed samples.",
   "positivity_percent": 15.6,
   "samples_analyzed": 237,
   "samples_collected": 257,
   "samples_positive": 37
  },
  "laboratory_status": [
   {
    "province": "Ituri",
    "samples_collected": 134,
    "samples_analyzed": 134,
    "samples_positive": 34,
    "positivity_percent": 25.0
   },
   {
    "province": "Nord-Kivu",
    "samples_collected": 117,
    "samples_analyzed": 97,
    "samples_positive": 3,
    "positivity_percent": 3.1
   },
   {
    "province": "Sud-Kivu",
    "samples_collected": 6,
    "samples_analyzed": 6,
    "samples_positive": 0,
    "positivity_percent": 0.0
   }
  ],
  "narrative": {
   "care_continuity": [
    "End-of-day isolation stood at 385 patients (205 confirmed, 180 suspected) at 74.9% global occupancy.",
    "Ituri isolation occupancy was 85.3% with 313 patients isolated at end day; Nord-Kivu was 57.3% with 59 and Sud-Kivu 29.5% with 13.",
    "One escape was recorded in Ituri during the cycle; 16 recovered exits were recorded, all in Ituri."
   ],
   "highlights": [
    "37 new confirmed cases including 5 confirmed deaths were reported for 2026-06-24, in Ituri (34 including 4 deaths) and Nord-Kivu (3 including 1 death).",
    "New confirmed cases were distributed across Rwampara (12), Bunia (10), Nyankunde (5), Mongbwalu (4), Bambu (2) and Tchomia (1) in Ituri, and Butembo (2), Katwa (1) in Nord-Kivu.",
    "8 additional deaths were recorded among previously confirmed CTE patients in Ituri (Bunia 4, Mongbwalu 2, Nyankunde 1, Rwampara 1), bringing confirmed deaths to 304.",
    "16 patients were declared recovered in Ituri after negative control tests, bringing DRC cumulative recoveries to 138."
   ],
   "laboratory": [
    "SitRep41 reports Ituri 134 samples collected and analyzed with 34 positive (25.0%).",
    "Nord-Kivu received 117 samples, analyzed 97, with 3 positive (3.1%) and 20 still under analysis; Sud-Kivu collected and analyzed 6, all negative."
   ],
   "publication_context": [
    "INSP SitRep 41 reports through 2026-06-24 and was published on the INSP WordPress site on 2026-06-25T22:03:56Z (post 25054).",
    "The outbreak remains reported across 3 provinces and 34 of 104 health zones; no new affected health zone is reported in this SitRep.",
    "Ituri remains the epicenter with 1054 of 1155 DRC confirmed cases (91.3%).",
    "Nord-Kivu stands at 98 confirmed cases and keeps the highest provincial confirmed-case fatality ratio at 54.1%, led by Oicha (66.7%), Kyondo (66.7%), Katwa (60.6%), and Beni (60.0%)."
   ],
   "redactions": [
    "Page contact details and operational names, if present outside table facts, are intentionally not promoted into public evidence text."
   ],
   "surveillance": [
    "903 alerts were reported and 744 investigated, producing an 82.4% investigation rate; Nord-Kivu investigated 507 of 665 alerts (76.2%).",
    "154 suspected cases of the day were validated, including 40 deceased validated alerts.",
    "9,305 contacts were under follow-up and 7,368 were seen, producing 79.2% follow-up coverage.",
    "311 new contacts were listed across 9 Ituri health zones; 99 contacts completed 21-day follow-up successfully, including 79 in Nord-Kivu and 20 in Ituri."
   ]
  },
  "operational_tables": {
   "alerts_by_province": [
    {
     "province": "Ituri",
     "alerts_reported": 214,
     "alerts_investigated": 214,
     "alerts_validated_living": 63,
     "alerts_validated_deaths": 34,
     "investigation_rate_pct": 100.0,
     "suspected_cases_day": 97
    },
    {
     "province": "Nord-Kivu",
     "alerts_reported": 665,
     "alerts_investigated": 507,
     "alerts_validated_living": 45,
     "alerts_validated_deaths": 6,
     "investigation_rate_pct": 76.2,
     "suspected_cases_day": 51
    },
    {
     "province": "Sud-Kivu",
     "alerts_reported": 24,
     "alerts_investigated": 23,
     "alerts_validated_living": 6,
     "alerts_validated_deaths": 0,
     "investigation_rate_pct": 95.8,
     "suspected_cases_day": 6
    }
   ],
   "alerts_total": {
    "alerts_investigated": 744,
    "alerts_reported": 903,
    "alerts_validated_deaths": 40,
    "alerts_validated_living": 114,
    "data_gap_note": "Report (J-1) 94; new alerts 809; 311 new contacts listed across 9 Ituri health zones; 99 contacts completed 21-day follow-up (79 Nord-Kivu, 20 Ituri).",
    "investigation_rate_pct": 82.4,
    "suspected_cases_day": 154
   },
   "challenges": [
    {
     "topic": "case_load_and_capacity",
     "finding": "Ituri CTE occupancy stood at 85.3% with an estimated gap of about 20 isolation centers.",
     "response": "Accelerate CTE construction and expansion and deploy additional temporary isolation structures."
    },
    {
     "topic": "contact_followup_gap",
     "finding": "Contact follow-up reached 79.2% versus the 95% target (a 15.8 pp gap).",
     "response": "Train, deploy, and motivate community relays (RECO) with reinforced supervision."
    },
    {
     "topic": "unlocalized_confirmed_cases",
     "finding": "Seventeen Ituri confirmed cases remain not yet precisely ventilated by health zone.",
     "response": "Conduct data reconciliation, duplicate cleanup, field verification, and reclassification."
    },
    {
     "topic": "health_worker_infections",
     "finding": "The SitRep41 challenge table reports 78 health-worker infections and 18 deaths (CFR 23.1%).",
     "response": "Reinforce IPC/WASH supplies (PPE, chlorine), supervision, and training."
    },
    {
     "topic": "lab_backlog",
     "finding": "Nord-Kivu carries a laboratory sample backlog and late diagnosis amid a 54.1% provincial CFR, with 20 samples still under analysis.",
     "response": "Deploy a laboratory catch-up plan and reinforce diagnostic capacity."
    }
   ],
   "contacts_by_province": [
    {
     "province": "Ituri",
     "contacts_under_follow_up": 7103,
     "contacts_seen_24h": 5545,
     "followup_rate_pct": 78.1
    },
    {
     "province": "Nord-Kivu",
     "contacts_under_follow_up": 2184,
     "contacts_seen_24h": 1805,
     "followup_rate_pct": 82.6
    },
    {
     "province": "Sud-Kivu",
     "contacts_under_follow_up": 18,
     "contacts_seen_24h": 18,
     "followup_rate_pct": 100.0
    }
   ],
   "contacts_total": {
    "contacts_seen_24h": 7368,
    "contacts_under_follow_up": 9305,
    "data_gap_note": "311 new contacts were listed across 9 Ituri health zones; 99 contacts completed 21-day follow-up (79 Nord-Kivu, 20 Ituri).",
    "followup_rate_pct": 79.2
   },
   "new_contacts_listed": [
    {
     "new_contacts": 311,
     "province": "Ituri",
     "zone": "9 ZS (non enumerees dans le SitRep)"
    }
   ],
   "patient_movement_by_province": [
    {
     "province": "Ituri",
     "admissions_24h": 59,
     "confirmed_in_isolation": 188,
     "deaths_suspect_or_confirmed_24h": 14,
     "escaped_suspect_or_confirmed_24h": 1,
     "non_cases_24h": 37,
     "non_cases_or_recovered_24h": 53,
     "occupancy_percent": 85.3,
     "patients_in_bed_j_minus_1": 322,
     "patients_in_isolation_end_day": 313,
     "recovered_24h": 16,
     "suspects_in_isolation": 125,
     "total_exits_24h": 68,
     "transferred_to_hgr_24h": 0
    },
    {
     "province": "Nord-Kivu",
     "admissions_24h": 8,
     "confirmed_in_isolation": 17,
     "deaths_suspect_or_confirmed_24h": 0,
     "escaped_suspect_or_confirmed_24h": 0,
     "non_cases_24h": 5,
     "non_cases_or_recovered_24h": 5,
     "occupancy_percent": 57.3,
     "patients_in_bed_j_minus_1": 56,
     "patients_in_isolation_end_day": 59,
     "recovered_24h": 0,
     "suspects_in_isolation": 42,
     "total_exits_24h": 5,
     "transferred_to_hgr_24h": 0
    },
    {
     "province": "Sud-Kivu",
     "admissions_24h": 6,
     "confirmed_in_isolation": 0,
     "deaths_suspect_or_confirmed_24h": 0,
     "escaped_suspect_or_confirmed_24h": 0,
     "non_cases_24h": 5,
     "non_cases_or_recovered_24h": 5,
     "occupancy_percent": 29.5,
     "patients_in_bed_j_minus_1": 12,
     "patients_in_isolation_end_day": 13,
     "recovered_24h": 0,
     "suspects_in_isolation": 13,
     "total_exits_24h": 5,
     "transferred_to_hgr_24h": 0
    }
   ],
   "patient_movement_total": {
    "admissions_24h": 73,
    "confirmed_in_isolation": 205,
    "deaths_suspect_or_confirmed_24h": 14,
    "escaped_suspect_or_confirmed_24h": 1,
    "non_cases_24h": 47,
    "non_cases_or_recovered_24h": 63,
    "occupancy_percent": 74.9,
    "patients_in_bed_j_minus_1": 390,
    "patients_in_isolation_end_day": 385,
    "recovered_24h": 16,
    "suspects_in_isolation": 180,
    "total_exits_24h": 78,
    "transferred_to_hgr_24h": 0
   },
   "poe_poc_ituri": {
    "activated_poc_denominator": 55,
    "activated_poc_numerator": 47,
    "activated_poc_percent": 85.5,
    "alerts_notified": 3,
    "alerts_transferred_to_ct_cte_or_eds": 0,
    "alerts_validated": 1,
    "contacts_intercepted_today": 0,
    "handwashed_percent": 92.4,
    "results_within_24h_percent": 0.0,
    "sensitized_percent": 94.7,
    "travelers_passed": 92533,
    "travelers_screened_percent": 96.2
   },
   "priorities": [
    {
     "pillar": "Source review",
     "priority": "Resolve the 17 unventilated Ituri confirmed cases without distributing them to named health zones",
     "timeline": "Before zone-level attribution use"
    },
    {
     "pillar": "Case management",
     "priority": "Protect Ituri isolation capacity (85.3% occupancy) and close the reported gap of about 20 isolation centers",
     "timeline": "Urgent"
    },
    {
     "pillar": "Surveillance",
     "priority": "Improve contact follow-up (79.2% vs 95% target) and clear the Nord-Kivu laboratory backlog (20 samples pending) given the 54.1% provincial CFR",
     "timeline": "Urgent / next SitRep review"
    }
   ]
  },
  "patients_en_isolement_hospitalisation": 385,
  "suspected_cases_day": 154,
  "suspected_deaths_day": 40,
  "source_ids": [
   "inrb-sitrep-041-2026-06-24",
   "uganda-moh-ebola-update-2026-06-21"
  ],
  "uganda_anchor_source_ids": [
   "uganda-moh-ebola-update-2026-06-21"
  ],
  "preserved_conflicts": [
   "SitRep41 headline is DRC-only (1155 confirmed / 304 confirmed deaths across Ituri, Nord-Kivu, Sud-Kivu); the country-scope public snapshot adds the latest reviewed Uganda component separately.",
   "The 1,155 confirmed total is marked re-actualized after DHIS2 cleaning/harmonization across health zones, laboratories, and care structures; treat the +37 confirmed and +13 confirmed deaths as official revised deltas, not raw incident-line-list deltas.",
   "SitRep41 carries an explicit Ituri residual of 17 confirmed cases in zones not yet identified; these counts are public but not mappable to named health zones.",
   "Ituri recorded 8 additional deaths among previously confirmed CTE patients (Bunia 4, Mongbwalu 2, Nyankunde 1, Rwampara 1); with the 5 deaths among the 37 new confirmed cases, the confirmed-death total advances by 13 to 304.",
   "Daily suspected cases (154) and the 40 deceased validated alerts are current-cycle validated alert outputs, not cumulative suspected stock or cumulative confirmed deaths.",
   "Uganda anchor remains 20 cumulative confirmed cases (2 deaths, 11 recoveries) per the Uganda MoH EVD daily dashboard, carried forward unchanged from SitRep40; the Uganda dashboard/API was unreachable this cycle, so this is a carried-forward anchor and not a fresh confirmation (INSP reports DRC only).",
   "The France imported confirmed case (a reanimation physician who worked the Bunia response for ALIMA and developed signs in transit) is an exportation/importation signal, not a DRC denominator addition.",
   "An INSP expert deployed to Ituri died in Kinshasa on 24 June 2026 after a hypertensive episode; two samples were negative for MVE, so this is not counted as a confirmed case or death.",
   "North-Kivu patient-movement figures (Table 6) are dated 2026-06-23 because 24 June data were unavailable at consolidation; the headline counts and the health-zone table remain 24 June.",
   "The SitRep highlights paragraph dates the 37 new confirmed cases 23 June 2026, while the report title, Table 1, and all detail tables date them 24 June 2026; treated as 2026-06-24 per the table and title basis.",
   "The 90-day RDC-Uganda cross-border response plan (joint laboratory and clinical-care capacity, starting with the strategic Aru zone) is operational readiness and coordination evidence, not proof of realized capacity."
  ],
  "province_operational": {
   "byProvince": {
    "Ituri": {
     "admissions24h": 59,
     "confirmedInIsolation": 188,
     "contactsSeen": 5545,
     "contactsUnderFollowUp": 7103,
     "escapes24h": 1,
     "followUpCoveragePct": 78.1,
     "patientsInIsolation": 313,
     "suspectsInIsolation": 125
    },
    "Nord-Kivu": {
     "admissions24h": 8,
     "confirmedInIsolation": 17,
     "contactsSeen": 1805,
     "contactsUnderFollowUp": 2184,
     "escapes24h": 0,
     "followUpCoveragePct": 82.6,
     "patientsInIsolation": 59,
     "suspectsInIsolation": 42
    },
    "Sud-Kivu": {
     "admissions24h": 6,
     "confirmedInIsolation": 0,
     "contactsSeen": 18,
     "contactsUnderFollowUp": 18,
     "escapes24h": 0,
     "followUpCoveragePct": 100.0,
     "patientsInIsolation": 13,
     "suspectsInIsolation": 13
    }
   },
   "national": {
    "admissions24h": 73,
    "confirmedInIsolation": 205,
    "contactsSeen": 7368,
    "contactsUnderFollowUp": 9305,
    "escapes24h": 1,
    "followUpCoveragePct": 79.2,
    "patientsInIsolation": 385,
    "suspectsInIsolation": 180
   }
  }
 },
 "published_at": "2026-06-25T22:03:56Z",
 "review": {
  "evidence_chain_id": "ec:lovs:data:inrb-sitrep-041-visual-promotion:2026-06-24",
  "ready_for_model_use": true,
  "review_notes": [
   "SitRep #041 (report date 2026-06-24; INSP WordPress post 25054 published 2026-06-25T22:03:56Z; embedded PDF media 25055). PDF sha256 656822f7d31650f2b46c602c7decd620fd7ebb4b9f92d5e0bde730b8184182c2, 11 pages. Title N041/MVB_24/06/2026; treated as report-date 2026-06-24.",
   "DRC headline 1155 confirmed / 304 confirmed deaths (CFR 26.3%); +37 confirmed and +13 confirmed deaths vs SitRep40. The 37 new confirmed (Ituri 34, Nord-Kivu 3) carried 5 deaths; a further 8 deaths occurred among previously confirmed Ituri CTE patients, totalling the +13.",
   "The 1,155 total is flagged re-actualized after DHIS2 cleaning/harmonization; deltas are official revised deltas.",
   "The affected-zone count remains 34/104. No new affected health zone is reported, so no new map geometry/centroid is required this cycle. The zone set is identical to SitRep40.",
   "Health-zone rows reconcile to 1155 confirmed / 304 deaths: 1138 named confirmed cases plus 17 Ituri cases awaiting ventilation, with all 304 confirmed deaths named-zone attributed.",
   "Recovered advanced to 138 DRC cumulative (+16, all Ituri; 129 Ituri / 7 Nord-Kivu / 2 Sud-Kivu). Uganda anchor carried forward unchanged at 20 cumulative cases / 2 deaths / 11 recoveries (dashboard unreachable this cycle), so country-scope is 1175 confirmed / 306 deaths / 149 recovered.",
   "Laboratory throughput promoted from section 4.3: Ituri 134 collected/analyzed, 34 positive; Nord-Kivu 117 received, 97 analyzed, 3 positive, 20 pending; Sud-Kivu 6 collected/analyzed, 0 positive.",
   "Operational data captured: 903 alerts (744 investigated, 82.4%; Nord-Kivu 507/665, 76.2%), 154 suspected cases of the day (40 deceased validated alerts), 9,305 contacts under follow-up (79.2%), 385 in isolation (205 confirmed / 180 suspected, 74.9% occupancy), 311 new contacts (9 Ituri zones), PoC activation 86.8% (59/68) with 264,124 travelers passed.",
   "France imported case and the Kinshasa INSP-expert death (two negative MVE samples) are recorded as context only, not added to DRC counts. North-Kivu patient-movement figures are dated 23 June (24 June unavailable). Promoted as table facts only."
  ],
  "reviewed_at": "2026-06-26T02:00:00Z",
  "reviewed_by": "bdbv-snapshot-prep-manager",
  "source_review_status": "reviewed"
 },
 "schema_version": "sitrep-promotion/v1",
 "sitrep_number": 41,
 "source_id": "inrb-sitrep-041-2026-06-24",
 "source_url": "https://insp.cd/wp-content/uploads/2026/06/Final-SitRep_MVE_RDC_N%C2%B0041_24_06_2026-1.pdf",
 "status": "reviewed"
}
