{
  "_meta": {
    "schema_version": 1,
    "purpose": "Immutable, append-only ledger of pre-committed LOVS methodology calibration points for the BDBV 2026 outbreak. Each block is a pin moment: a set of corridors committed on a fixed date, with a fixed model uncertainty range and a fixed resolution date. refresh_pipeline.py reads the active (unresolved) blocks and carries their points forward UNCHANGED into every snapshot; it never re-derives them from the current run's corridor ranking. That carry-forward is the pre-commitment contract the calibration scoring depends on.",
    "doctrine": [
      "Pin once. A block's points, model ranges, pin date, and resolution date are never edited after commit.",
      "Carry forward. A daily refresh re-emits the active points verbatim. Re-deriving them from freshly ranked corridors would silently overwrite an earlier commitment and break pre-commitment.",
      "Append only. New calibration points are added as a NEW block at an explicit pin moment, never by mutating an existing block.",
      "Resolve by appending. On a resolution date, score the due points against public reports and append the outcome; the original pinned range is never altered.",
      "Early-lock when monotonic-safe. A point may have its outcome appended before its block's resolves_at iff a new lab-confirmed case appears in the target zone strictly inside [pinned_at, resolves_at]: the YES outcome is monotonic-safe (cannot flip back) and the append is structurally identical to a resolution-date append. The early-lock authorization applies only to YES outcomes; resolved_no outcomes wait for resolves_at to remove ambiguity about late-arriving evidence."
    ],
    "id_derivation": "hypothesis_id = 'calibration-point:bdbv-uga-cod-2026:30d:' + sha256('bdbv-uga-cod-2026|{source}|{target}|{horizon_days}d|{pinned_at}')[:10]. refresh_pipeline._calibration_point_id reproduces this and verifies every point's id against its corridor at load time.",
    "consumed_by": "refresh_pipeline.carry_forward_calibration(as_of) -> writes data/live-bdbv-2026-output.json mode_b_hypotheses and resolves_at. See PIPELINE.md, section (c) Calibration and resolution.",
    "licensing": "CC BY 4.0 (per LICENSES.md) covers this file's schema, structure, and authored annotations. The model ranges are original derived outputs of the LOVS pipeline.",
    "outbreak_id": "bdbv-uga-cod-2026",
    "scope_id": "epi:bdbv-uga-cod-2026"
  },
  "blocks": [
    {
      "block_id": "calibration-block:bdbv-uga-cod-2026:2026-05-20",
      "pinned_at": "2026-05-20",
      "resolves_at": "2026-06-19T23:59:59Z",
      "horizon_days": 30,
      "status": "active",
      "rationale": "First calibration block. The four corridors ranked highest by ascertainment-adjusted 30-day export risk in the 20 May 2026 PHEIC-era snapshot, pinned as the method's pre-committed uncertainty test. Carried forward unchanged on every later refresh; scored against public reports on 2026-06-19.",
      "points": [
        {
          "hypothesis_id": "calibration-point:bdbv-uga-cod-2026:30d:e77003de63",
          "corridor": "bunia -> kampala-uga",
          "source": "bunia",
          "target": "kampala-uga",
          "horizon_days": 30,
          "risk_adj_50": [
            0.229,
            0.523
          ],
          "outcome": 1,
          "resolved_as_of": "2026-05-23",
          "outcome_evidence": {
            "source_id": "uga-moh-2026-05-23-kampala-three-new",
            "source_url": "https://www.aljazeera.com/news/2026/5/23/uganda-confirms-three-new-ebola-cases-bringing-total-to-five",
            "classification": "resolution_eligible",
            "confirmed_in_window": true,
            "first_in_window_confirmation_date": "2026-05-23"
          },
          "resolution_provenance": "calibration_resolver.py report 2026-05-26; early-lock monotonic-safe per ledger _meta.doctrine[3]"
        },
        {
          "hypothesis_id": "calibration-point:bdbv-uga-cod-2026:30d:bede8179ea",
          "corridor": "rwampara -> bundibugyo-uga",
          "source": "rwampara",
          "target": "bundibugyo-uga",
          "horizon_days": 30,
          "risk_adj_50": [
            0.227,
            0.523
          ]
        },
        {
          "hypothesis_id": "calibration-point:bdbv-uga-cod-2026:30d:d853267eed",
          "corridor": "mongbwalu -> beni-cod",
          "source": "mongbwalu",
          "target": "beni-cod",
          "horizon_days": 30,
          "risk_adj_50": [
            0.218,
            0.522
          ]
        },
        {
          "hypothesis_id": "calibration-point:bdbv-uga-cod-2026:30d:cf92d9f82b",
          "corridor": "rwampara -> kasese-uga",
          "source": "rwampara",
          "target": "kasese-uga",
          "horizon_days": 30,
          "risk_adj_50": [
            0.209,
            0.515
          ]
        }
      ]
    },
    {
      "block_id": "calibration-block:bdbv-uga-cod-2026:2026-05-21",
      "pinned_at": "2026-05-21",
      "resolves_at": "2026-06-20T23:59:59Z",
      "horizon_days": 30,
      "status": "active",
      "rationale": "Second calibration block, pinned before publication of the 21 May 2026 snapshot. This block augments the initial top-four block with a designed sample across the current watchlist's relative high/mid/low bands, cross-border and in-country corridors, and likely positive / likely negative controls. Because the aggregate-input model still clusters all 18 watchlist corridors in a narrow probability band, these are relative tiers within the 21 May watchlist, not absolute low/medium/high probabilities.",
      "points": [
        {
          "hypothesis_id": "calibration-point:bdbv-uga-cod-2026:30d:b4a76ed77f",
          "corridor": "bunia -> kasese-uga",
          "source": "bunia",
          "target": "kasese-uga",
          "horizon_days": 30,
          "risk_adj_50": [
            0.22,
            0.553
          ],
          "selection_role": "relative-high cross-border watch corridor",
          "risk_tier": "relative_high",
          "geography_class": "cross_border",
          "control_role": "watchlist_high"
        },
        {
          "hypothesis_id": "calibration-point:bdbv-uga-cod-2026:30d:e3efe4dd95",
          "corridor": "bunia -> beni-cod",
          "source": "bunia",
          "target": "beni-cod",
          "horizon_days": 30,
          "risk_adj_50": [
            0.243,
            0.525
          ],
          "selection_role": "relative-high in-country likely-positive control",
          "risk_tier": "relative_high",
          "geography_class": "in_country",
          "control_role": "likely_positive"
        },
        {
          "hypothesis_id": "calibration-point:bdbv-uga-cod-2026:30d:92b62f4c0c",
          "corridor": "rwampara -> kampala-uga",
          "source": "rwampara",
          "target": "kampala-uga",
          "horizon_days": 30,
          "risk_adj_50": [
            0.218,
            0.515
          ],
          "selection_role": "mid-band cross-border imported-case positive control",
          "risk_tier": "relative_mid",
          "geography_class": "cross_border",
          "control_role": "likely_positive",
          "outcome": 1,
          "resolved_as_of": "2026-05-23",
          "outcome_evidence": {
            "source_id": "uga-moh-2026-05-23-kampala-three-new",
            "source_url": "https://www.aljazeera.com/news/2026/5/23/uganda-confirms-three-new-ebola-cases-bringing-total-to-five",
            "classification": "resolution_eligible",
            "confirmed_in_window": true,
            "first_in_window_confirmation_date": "2026-05-23"
          },
          "resolution_provenance": "calibration_resolver.py report 2026-05-26; early-lock monotonic-safe per ledger _meta.doctrine[3]"
        },
        {
          "hypothesis_id": "calibration-point:bdbv-uga-cod-2026:30d:d8ee2a62a9",
          "corridor": "mongbwalu -> kasese-uga",
          "source": "mongbwalu",
          "target": "kasese-uga",
          "horizon_days": 30,
          "risk_adj_50": [
            0.236,
            0.519
          ],
          "selection_role": "mid-band cross-border watch corridor",
          "risk_tier": "relative_mid",
          "geography_class": "cross_border",
          "control_role": "watchlist_mid"
        },
        {
          "hypothesis_id": "calibration-point:bdbv-uga-cod-2026:30d:f3f474294b",
          "corridor": "rwampara -> beni-cod",
          "source": "rwampara",
          "target": "beni-cod",
          "horizon_days": 30,
          "risk_adj_50": [
            0.236,
            0.518
          ],
          "selection_role": "mid-band in-country likely-positive control",
          "risk_tier": "relative_mid",
          "geography_class": "in_country",
          "control_role": "likely_positive"
        },
        {
          "hypothesis_id": "calibration-point:bdbv-uga-cod-2026:30d:deb53c5269",
          "corridor": "bunia -> arua-uga",
          "source": "bunia",
          "target": "arua-uga",
          "horizon_days": 30,
          "risk_adj_50": [
            0.236,
            0.52
          ],
          "selection_role": "mid-band cross-border blindspot watch corridor",
          "risk_tier": "relative_mid",
          "geography_class": "cross_border",
          "control_role": "blindspot_watch"
        },
        {
          "hypothesis_id": "calibration-point:bdbv-uga-cod-2026:30d:db608ab7c7",
          "corridor": "rwampara -> arua-uga",
          "source": "rwampara",
          "target": "arua-uga",
          "horizon_days": 30,
          "risk_adj_50": [
            0.221,
            0.494
          ],
          "selection_role": "relative-low cross-border likely-negative control",
          "risk_tier": "relative_low",
          "geography_class": "cross_border",
          "control_role": "likely_negative"
        },
        {
          "hypothesis_id": "calibration-point:bdbv-uga-cod-2026:30d:7da36f72ef",
          "corridor": "mongbwalu -> nebbi-uga",
          "source": "mongbwalu",
          "target": "nebbi-uga",
          "horizon_days": 30,
          "risk_adj_50": [
            0.222,
            0.51
          ],
          "selection_role": "relative-low cross-border likely-negative control",
          "risk_tier": "relative_low",
          "geography_class": "cross_border",
          "control_role": "likely_negative"
        }
      ]
    },
    {
      "block_id": "calibration-block:bdbv-uga-cod-2026:2026-05-26",
      "pinned_at": "2026-05-26",
      "resolves_at": "2026-06-25T23:59:59Z",
      "horizon_days": 30,
      "status": "active",
      "rationale": "Third calibration block. Graduates Goma (goma-cod) from geographic-anchor-not-in-calibration to a pinned candidate target on 2026-05-26 per founder direction (see .process/2026-05-26-pre-refresh-decisions/follow-up-after-pushback.md, Thread 2 path A). Pins the three Ituri source HZs -> goma-cod corridors at the ascertainment-adjusted 50% intervals from the 2026-05-26 pipeline run with goma-cod added to candidate_target_zones. Pre-pin prior context (NOT a resolution event): one laboratory-confirmed BDBV case in Goma on 2026-05-17, a woman who travelled from Ituri Province (per data/zones.json:goma-cod and data/external_sources/bdbv-2026.observed.json). Doctrine[4] early-lock will fire only on a new lab-confirmed case landing in Goma strictly inside [2026-05-26, 2026-06-25T23:59:59Z]; the 17-May case is outside that window and is therefore not a doctrine[4] trigger. Carried forward unchanged on every later refresh; scored against public reports on 2026-06-25.",
      "points": [
        {
          "hypothesis_id": "calibration-point:bdbv-uga-cod-2026:30d:269808f993",
          "corridor": "bunia -> goma-cod",
          "source": "bunia",
          "target": "goma-cod",
          "horizon_days": 30,
          "risk_adj_50": [
            0.1024,
            0.2669
          ],
          "selection_role": "Ituri-source -> Goma graduation pin (Ituri provincial capital)",
          "risk_tier": "relative_mid",
          "geography_class": "in_country",
          "control_role": "watchlist_mid"
        },
        {
          "hypothesis_id": "calibration-point:bdbv-uga-cod-2026:30d:d057737062",
          "corridor": "rwampara -> goma-cod",
          "source": "rwampara",
          "target": "goma-cod",
          "horizon_days": 30,
          "risk_adj_50": [
            0.2034,
            0.4589
          ],
          "selection_role": "Ituri-source -> Goma graduation pin (largest Ituri source zone by case count)",
          "risk_tier": "relative_high",
          "geography_class": "in_country",
          "control_role": "watchlist_high"
        },
        {
          "hypothesis_id": "calibration-point:bdbv-uga-cod-2026:30d:f4e8a4499d",
          "corridor": "mongbwalu -> goma-cod",
          "source": "mongbwalu",
          "target": "goma-cod",
          "horizon_days": 30,
          "risk_adj_50": [
            0.0955,
            0.2518
          ],
          "selection_role": "Ituri-source -> Goma graduation pin (Ituri mining-area source zone)",
          "risk_tier": "relative_mid",
          "geography_class": "in_country",
          "control_role": "watchlist_mid"
        }
      ]
    },
    {
      "block_id": "calibration-block:bdbv-uga-cod-2026:2026-06-04",
      "pinned_at": "2026-06-04",
      "resolves_at": "2026-07-04T23:59:59Z",
      "horizon_days": 30,
      "status": "active",
      "rationale": "Fourth calibration block. Pins the 2026-06-04 west/SSD corridor expansion: two new candidate targets (yei-ssd, kisangani-cod) graduate to pinned corridor endpoints, and the four highest-signal source-to-target corridors to them are committed at the ascertainment-adjusted 50% intervals from the 2026-06-04 pipeline run with both targets added to candidate_target_zones. yei-ssd tests northward cross-border exportation to South Sudan (West Nile / Morobo-Kaya axis); kisangani-cod tests the westward Tshopo / Congo-river axis (RN4 via Mambasa and Bafwasende), a no-PCR surveillance gap. The aru -> yei-ssd point is a designed geography-vs-load blindspot probe (frontier geography flags Aru while the case-load model rates it low). Corridor basis: WHO DON603 (2026-05-29). Carried forward unchanged on every later refresh; scored against public reports on 2026-07-04.",
      "points": [
        {
          "hypothesis_id": "calibration-point:bdbv-uga-cod-2026:30d:d0873f439b",
          "corridor": "bunia -> yei-ssd",
          "source": "bunia",
          "target": "yei-ssd",
          "horizon_days": 30,
          "risk_adj_50": [
            0.3889,
            0.7337
          ],
          "selection_role": "Highest-load Ituri source -> South Sudan (Yei) cross-border pin; the northward-exportation calibration point",
          "risk_tier": "relative_high",
          "geography_class": "cross_border",
          "control_role": "watchlist_mid"
        },
        {
          "hypothesis_id": "calibration-point:bdbv-uga-cod-2026:30d:75a76e11e6",
          "corridor": "aru -> yei-ssd",
          "source": "aru",
          "target": "yei-ssd",
          "horizon_days": 30,
          "risk_adj_50": [
            0.0121,
            0.0325
          ],
          "selection_role": "Northern frontier source (Aru territory borders South Sudan) -> Yei; geography-vs-load blindspot, geography flags Aru as the gateway while the case-load model rates it low",
          "risk_tier": "relative_low",
          "geography_class": "cross_border",
          "control_role": "blindspot_watch"
        },
        {
          "hypothesis_id": "calibration-point:bdbv-uga-cod-2026:30d:37a9144af6",
          "corridor": "bunia -> kisangani-cod",
          "source": "bunia",
          "target": "kisangani-cod",
          "horizon_days": 30,
          "risk_adj_50": [
            0.3658,
            0.7128
          ],
          "selection_role": "Highest-load Ituri source -> Tshopo/Kisangani west axis (RN4 via Mambasa and Bafwasende); the westward-to-the-river-system calibration point",
          "risk_tier": "relative_high",
          "geography_class": "in_country",
          "control_role": "watchlist_mid"
        },
        {
          "hypothesis_id": "calibration-point:bdbv-uga-cod-2026:30d:f056457650",
          "corridor": "mongbwalu -> kisangani-cod",
          "source": "mongbwalu",
          "target": "kisangani-cod",
          "horizon_days": 30,
          "risk_adj_50": [
            0.2329,
            0.5228
          ],
          "selection_role": "Ituri mining-area origin source -> Tshopo/Kisangani west axis",
          "risk_tier": "relative_mid",
          "geography_class": "in_country",
          "control_role": "watchlist_mid"
        }
      ]
    }
  ]
}
