{
  "as_of": "2026-05-31T23:59:59Z",
  "data_as_of": "2026-05-26",
  "outbreak_id": "bdbv-uga-cod-2026",
  "reported_counts": {
    "confirmed": {
      "min": 263,
      "max": 282,
      "primary": 282,
      "primary_source_id": "inrb-sitrep-016-2026-05-30",
      "conflicting_source_ids": [
        "inrb-sitrep-015-2026-05-29",
        "ecdc-bdbv-drc-uga-2026-05-27",
        "who-pheic-2026-05-17",
        "ecdc-bdbv-drc-uga-2026-05-19",
        "wikipedia-2026-ituri-epidemic-2026-05-20",
        "who-dg-remarks-bdbv-2026-05-20",
        "cdc-current-situation-2026-05-21",
        "who-dg-remarks-bdbv-2026-05-22",
        "cdc-current-situation-2026-05-23",
        "drc-moh-epidemie-dashboard-sitrep-009-graphql-2026-05-24",
        "cdc-current-situation-2026-05-24",
        "ecdc-bdbv-drc-uga-2026-05-25",
        "cdc-current-situation-2026-05-25",
        "ecdc-bdbv-drc-uga-2026-05-26",
        "inrb-umie-ebola-drc-2026-build-2026-05-28-bb8b7d5"
      ],
      "carried_forward_from": "2026-05-30T23:59:59Z",
      "carried_forward_reason": "awaiting_next_publication"
    },
    "confirmed_active": {
      "min": 238,
      "max": 238,
      "primary": 238,
      "primary_source_id": "inrb-sitrep-016-2026-05-30",
      "conflicting_source_ids": [],
      "carried_forward_from": "2026-05-30T23:59:59Z",
      "carried_forward_reason": "awaiting_next_publication"
    },
    "recovered": {
      "min": 2,
      "max": 2,
      "primary": 2,
      "primary_source_id": "inrb-sitrep-016-2026-05-30",
      "conflicting_source_ids": [],
      "carried_forward_from": "2026-05-30T23:59:59Z",
      "carried_forward_reason": "awaiting_next_publication"
    },
    "suspected_active": {
      "min": 321,
      "max": 321,
      "primary": 321,
      "primary_source_id": "inrb-sitrep-016-2026-05-30",
      "conflicting_source_ids": [],
      "carried_forward_from": "2026-05-30T23:59:59Z",
      "carried_forward_reason": "awaiting_next_publication"
    },
    "suspected_cumulative": {
      "min": 395,
      "max": 3491,
      "primary": 3491,
      "primary_source_id": "inrb-sitrep-015-2026-05-29",
      "conflicting_source_ids": [
        "ecdc-bdbv-drc-uga-2026-05-27",
        "afro-sitrep-01-2026-05-18",
        "africa-cdc-phecs-2026-05-18",
        "wikipedia-2026-ituri-epidemic-2026-05-20",
        "ecdc-bdbv-drc-uga-2026-05-21",
        "cdc-current-situation-2026-05-21",
        "who-dg-remarks-bdbv-2026-05-22",
        "drc-moh-epidemie-dashboard-sitrep-009-graphql-2026-05-24",
        "cdc-current-situation-2026-05-24",
        "ecdc-bdbv-drc-uga-2026-05-25",
        "cdc-current-situation-2026-05-25",
        "ecdc-bdbv-drc-uga-2026-05-26",
        "inrb-umie-ebola-drc-2026-build-2026-05-28-bb8b7d5"
      ],
      "carried_forward_from": "2026-05-30T23:59:59Z",
      "carried_forward_reason": "awaiting_next_publication"
    }
  },
  "reported_deaths": {
    "confirmed": {
      "min": 43,
      "max": 43,
      "primary": 43,
      "primary_source_id": "inrb-sitrep-016-2026-05-30",
      "conflicting_source_ids": [
        "inrb-sitrep-015-2026-05-29",
        "inrb-umie-ebola-drc-2026-build-2026-05-28-bb8b7d5",
        "inrb-umie-ebola-drc-2026-build-2026-05-27-059661a",
        "ecdc-bdbv-drc-uga-2026-05-27"
      ],
      "carried_forward_from": "2026-05-30T23:59:59Z",
      "carried_forward_reason": "awaiting_next_publication"
    },
    "suspected": {
      "min": 106,
      "max": 246,
      "primary": 246,
      "primary_source_id": "inrb-umie-ebola-drc-2026-build-2026-05-28-bb8b7d5",
      "conflicting_source_ids": [
        "afro-sitrep-01-2026-05-18",
        "africa-cdc-phecs-2026-05-18",
        "ecdc-bdbv-drc-uga-2026-05-21",
        "wikipedia-2026-ituri-epidemic-2026-05-20",
        "who-dg-remarks-bdbv-2026-05-20",
        "cdc-current-situation-2026-05-21",
        "who-dg-remarks-bdbv-2026-05-22",
        "cdc-current-situation-2026-05-23",
        "cdc-current-situation-2026-05-24",
        "drc-moh-epidemie-dashboard-sitrep-009-graphql-2026-05-24",
        "ecdc-bdbv-drc-uga-2026-05-25",
        "cdc-current-situation-2026-05-25",
        "ecdc-bdbv-drc-uga-2026-05-26",
        "ecdc-bdbv-drc-uga-2026-05-27"
      ],
      "carried_forward_from": "2026-05-30T23:59:59Z",
      "carried_forward_reason": "awaiting_next_publication"
    }
  },
  "affected_zones": [
    "aru",
    "bambu",
    "bunia",
    "butembo",
    "damas",
    "goma-cod",
    "karisimbi-cod",
    "katwa",
    "kilo",
    "komanda",
    "mambasa",
    "miti-murhesa",
    "mongbwalu",
    "nizi",
    "nyankunde",
    "oicha",
    "rimba",
    "rwampara"
  ],
  "zone_attributed_counts": {
    "aru": {
      "confirmed": 1,
      "source_id": "inrb-umie-ebola-drc-2026-build-2026-05-28-bb8b7d5",
      "source_published_at": "2026-05-26",
      "original_zone_id": "aru",
      "province": ""
    },
    "bambu": {
      "confirmed": 0,
      "source_id": "inrb-umie-ebola-drc-2026-build-2026-05-28-bb8b7d5",
      "source_published_at": "2026-05-26",
      "original_zone_id": "bambu",
      "province": ""
    },
    "bunia": {
      "confirmed": 36,
      "source_id": "inrb-umie-ebola-drc-2026-build-2026-05-28-bb8b7d5",
      "source_published_at": "2026-05-26",
      "original_zone_id": "bunia",
      "province": ""
    },
    "butembo": {
      "confirmed": 3,
      "source_id": "inrb-umie-ebola-drc-2026-build-2026-05-28-bb8b7d5",
      "source_published_at": "2026-05-26",
      "original_zone_id": "butembo",
      "province": ""
    },
    "damas": {
      "confirmed": 0,
      "source_id": "inrb-umie-ebola-drc-2026-build-2026-05-28-bb8b7d5",
      "source_published_at": "2026-05-26",
      "original_zone_id": "damas",
      "province": ""
    },
    "goma-cod": {
      "confirmed": 1,
      "source_id": "inrb-umie-ebola-drc-2026-build-2026-05-28-bb8b7d5",
      "source_published_at": "2026-05-26",
      "original_zone_id": "goma-cod",
      "province": ""
    },
    "karisimbi-cod": {
      "confirmed": 0,
      "source_id": "inrb-umie-ebola-drc-2026-build-2026-05-28-bb8b7d5",
      "source_published_at": "2026-05-26",
      "original_zone_id": "karisimbi-cod",
      "province": ""
    },
    "katwa": {
      "confirmed": 0,
      "source_id": "inrb-umie-ebola-drc-2026-build-2026-05-28-bb8b7d5",
      "source_published_at": "2026-05-26",
      "original_zone_id": "katwa",
      "province": ""
    },
    "kilo": {
      "confirmed": 1,
      "source_id": "inrb-umie-ebola-drc-2026-build-2026-05-28-bb8b7d5",
      "source_published_at": "2026-05-26",
      "original_zone_id": "kilo",
      "province": ""
    },
    "komanda": {
      "confirmed": 0,
      "source_id": "inrb-umie-ebola-drc-2026-build-2026-05-28-bb8b7d5",
      "source_published_at": "2026-05-26",
      "original_zone_id": "komanda",
      "province": ""
    },
    "mambasa": {
      "confirmed": 0,
      "source_id": "inrb-umie-ebola-drc-2026-build-2026-05-28-bb8b7d5",
      "source_published_at": "2026-05-26",
      "original_zone_id": "mambasa",
      "province": ""
    },
    "miti-murhesa": {
      "confirmed": 1,
      "source_id": "inrb-umie-ebola-drc-2026-build-2026-05-28-bb8b7d5",
      "source_published_at": "2026-05-26",
      "original_zone_id": "miti-murhesa",
      "province": ""
    },
    "mongbwalu": {
      "confirmed": 20,
      "source_id": "inrb-umie-ebola-drc-2026-build-2026-05-28-bb8b7d5",
      "source_published_at": "2026-05-26",
      "original_zone_id": "mongbwalu",
      "province": ""
    },
    "nizi": {
      "confirmed": 2,
      "source_id": "inrb-umie-ebola-drc-2026-build-2026-05-28-bb8b7d5",
      "source_published_at": "2026-05-26",
      "original_zone_id": "nizi",
      "province": ""
    },
    "nyankunde": {
      "confirmed": 10,
      "source_id": "inrb-umie-ebola-drc-2026-build-2026-05-28-bb8b7d5",
      "source_published_at": "2026-05-26",
      "original_zone_id": "nyankunde",
      "province": ""
    },
    "oicha": {
      "confirmed": 1,
      "source_id": "inrb-umie-ebola-drc-2026-build-2026-05-28-bb8b7d5",
      "source_published_at": "2026-05-26",
      "original_zone_id": "oicha",
      "province": ""
    },
    "rimba": {
      "confirmed": 0,
      "source_id": "inrb-umie-ebola-drc-2026-build-2026-05-28-bb8b7d5",
      "source_published_at": "2026-05-26",
      "original_zone_id": "rimba",
      "province": ""
    },
    "rwampara": {
      "confirmed": 33,
      "source_id": "inrb-umie-ebola-drc-2026-build-2026-05-28-bb8b7d5",
      "source_published_at": "2026-05-26",
      "original_zone_id": "rwampara",
      "province": ""
    }
  },
  "zone_attributed_counts_source_ids": [
    "inrb-umie-ebola-drc-2026-build-2026-05-28-bb8b7d5"
  ],
  "source_review_geographies": [
    {
      "zone_id": "bambu",
      "zone_name": "Bambu",
      "province": "Ituri",
      "confirmed": 0,
      "suspected": 2,
      "deaths": 0,
      "source_id": "drc-moh-epidemie-dashboard-sitrep-008-graphql-2026-05-23",
      "source_published_at": "2026-05-23T00:00:00Z",
      "report_date": "2026-05-22",
      "publication_date": "2026-05-23",
      "table_semantics_status": "source_review",
      "model_use": "display_only_pending_table_semantics",
      "review_reasons": [
        "official_drc_moh_reported_row",
        "table_semantics_source_review"
      ]
    },
    {
      "zone_id": "bunia",
      "zone_name": "Bunia",
      "province": "Ituri",
      "confirmed": 6,
      "suspected": 32,
      "deaths": 1,
      "source_id": "drc-moh-epidemie-dashboard-sitrep-008-graphql-2026-05-23",
      "source_published_at": "2026-05-23T00:00:00Z",
      "report_date": "2026-05-22",
      "publication_date": "2026-05-23",
      "table_semantics_status": "source_review",
      "model_use": "display_only_pending_table_semantics",
      "review_reasons": [
        "official_drc_moh_reported_row",
        "table_semantics_source_review"
      ]
    },
    {
      "zone_id": "kilo",
      "zone_name": "Kilo",
      "province": "Ituri",
      "confirmed": 1,
      "suspected": 1,
      "deaths": 0,
      "source_id": "drc-moh-epidemie-dashboard-sitrep-008-graphql-2026-05-23",
      "source_published_at": "2026-05-23T00:00:00Z",
      "report_date": "2026-05-22",
      "publication_date": "2026-05-23",
      "table_semantics_status": "source_review",
      "model_use": "display_only_pending_table_semantics",
      "review_reasons": [
        "official_drc_moh_reported_row",
        "table_semantics_source_review"
      ]
    },
    {
      "zone_id": "mongbwalu",
      "zone_name": "Mongbwalu",
      "province": "Ituri",
      "confirmed": 1,
      "suspected": 10,
      "deaths": 0,
      "source_id": "drc-moh-epidemie-dashboard-sitrep-008-graphql-2026-05-23",
      "source_published_at": "2026-05-23T00:00:00Z",
      "report_date": "2026-05-22",
      "publication_date": "2026-05-23",
      "table_semantics_status": "source_review",
      "model_use": "display_only_pending_table_semantics",
      "review_reasons": [
        "official_drc_moh_reported_row",
        "table_semantics_source_review"
      ]
    },
    {
      "zone_id": "nizi",
      "zone_name": "Nizi",
      "province": "Ituri",
      "confirmed": 1,
      "suspected": 1,
      "deaths": 0,
      "source_id": "drc-moh-epidemie-dashboard-sitrep-008-graphql-2026-05-23",
      "source_published_at": "2026-05-23T00:00:00Z",
      "report_date": "2026-05-22",
      "publication_date": "2026-05-23",
      "table_semantics_status": "source_review",
      "model_use": "display_only_pending_table_semantics",
      "review_reasons": [
        "official_drc_moh_reported_row",
        "table_semantics_source_review"
      ]
    },
    {
      "zone_id": "nyankunde",
      "zone_name": "Nyakunde",
      "province": "Ituri",
      "confirmed": 2,
      "suspected": 9,
      "deaths": 0,
      "source_id": "drc-moh-epidemie-dashboard-sitrep-008-graphql-2026-05-23",
      "source_published_at": "2026-05-23T00:00:00Z",
      "report_date": "2026-05-22",
      "publication_date": "2026-05-23",
      "table_semantics_status": "source_review",
      "model_use": "display_only_pending_table_semantics",
      "review_reasons": [
        "official_drc_moh_reported_row",
        "table_semantics_source_review"
      ]
    },
    {
      "zone_id": "rwampara",
      "zone_name": "Rwampara",
      "province": "Ituri",
      "confirmed": 7,
      "suspected": 14,
      "deaths": 1,
      "source_id": "drc-moh-epidemie-dashboard-sitrep-008-graphql-2026-05-23",
      "source_published_at": "2026-05-23T00:00:00Z",
      "report_date": "2026-05-22",
      "publication_date": "2026-05-23",
      "table_semantics_status": "source_review",
      "model_use": "display_only_pending_table_semantics",
      "review_reasons": [
        "official_drc_moh_reported_row",
        "table_semantics_source_review"
      ]
    },
    {
      "zone_id": "miti-murhesa",
      "zone_name": "Miti Murhesa",
      "province": "Sud-Kivu",
      "confirmed": 1,
      "suspected": 1,
      "deaths": 1,
      "source_id": "drc-moh-epidemie-dashboard-sitrep-008-graphql-2026-05-23",
      "source_published_at": "2026-05-23T00:00:00Z",
      "report_date": "2026-05-22",
      "publication_date": "2026-05-23",
      "table_semantics_status": "source_review",
      "model_use": "display_only_pending_table_semantics",
      "review_reasons": [
        "official_drc_moh_reported_row",
        "table_semantics_source_review"
      ]
    },
    {
      "zone_id": "bunia",
      "zone_name": "Bunia",
      "province": "Ituri",
      "confirmed": 0,
      "suspected": 22,
      "deaths": 0,
      "source_id": "drc-moh-epidemie-dashboard-sitrep-009-graphql-2026-05-24",
      "source_published_at": "2026-05-24T00:00:00Z",
      "report_date": "None",
      "publication_date": "2026-05-24",
      "table_semantics_status": "source_review",
      "model_use": "display_only_pending_table_semantics",
      "review_reasons": [
        "official_drc_moh_reported_row",
        "table_semantics_source_review"
      ]
    },
    {
      "zone_id": "kilo",
      "zone_name": "Kilo",
      "province": "Ituri",
      "confirmed": 0,
      "suspected": 8,
      "deaths": 0,
      "source_id": "drc-moh-epidemie-dashboard-sitrep-009-graphql-2026-05-24",
      "source_published_at": "2026-05-24T00:00:00Z",
      "report_date": "None",
      "publication_date": "2026-05-24",
      "table_semantics_status": "source_review",
      "model_use": "display_only_pending_table_semantics",
      "review_reasons": [
        "official_drc_moh_reported_row",
        "table_semantics_source_review"
      ]
    },
    {
      "zone_id": "mongbwalu",
      "zone_name": "Mongbwalu",
      "province": "Ituri",
      "confirmed": 9,
      "suspected": 0,
      "deaths": 0,
      "source_id": "drc-moh-epidemie-dashboard-sitrep-009-graphql-2026-05-24",
      "source_published_at": "2026-05-24T00:00:00Z",
      "report_date": "None",
      "publication_date": "2026-05-24",
      "table_semantics_status": "source_review",
      "model_use": "display_only_pending_table_semantics",
      "review_reasons": [
        "official_drc_moh_reported_row",
        "table_semantics_source_review"
      ]
    },
    {
      "zone_id": "rwampara",
      "zone_name": "Rwampara",
      "province": "Ituri",
      "confirmed": 0,
      "suspected": 3,
      "deaths": 0,
      "source_id": "drc-moh-epidemie-dashboard-sitrep-009-graphql-2026-05-24",
      "source_published_at": "2026-05-24T00:00:00Z",
      "report_date": "None",
      "publication_date": "2026-05-24",
      "table_semantics_status": "source_review",
      "model_use": "display_only_pending_table_semantics",
      "review_reasons": [
        "official_drc_moh_reported_row",
        "table_semantics_source_review"
      ]
    },
    {
      "zone_id": "butembo",
      "zone_name": "Butembo",
      "province": "Nord-Kivu",
      "confirmed": 1,
      "suspected": 0,
      "deaths": 0,
      "source_id": "drc-moh-epidemie-dashboard-sitrep-009-graphql-2026-05-24",
      "source_published_at": "2026-05-24T00:00:00Z",
      "report_date": "None",
      "publication_date": "2026-05-24",
      "table_semantics_status": "source_review",
      "model_use": "display_only_pending_table_semantics",
      "review_reasons": [
        "official_drc_moh_reported_row",
        "table_semantics_source_review"
      ]
    }
  ],
  "sources": [
    "africa-cdc-phecs-2026-05-18",
    "afro-sitrep-01-2026-05-18",
    "afro-sitrep-01-pdf-2026-05-18",
    "cdc-current-situation-2026-05-21",
    "cdc-current-situation-2026-05-23",
    "cdc-current-situation-2026-05-24",
    "cdc-current-situation-2026-05-25",
    "drc-moh-epidemie-dashboard-sitrep-009-graphql-2026-05-24",
    "drc-moh-epidemie-dashboard-sitrep-mve-n-007-mvb-17-2026-pdf-2026-05-22",
    "ecdc-bdbv-drc-uga-2026-05-19",
    "ecdc-bdbv-drc-uga-2026-05-21",
    "ecdc-bdbv-drc-uga-2026-05-25",
    "ecdc-bdbv-drc-uga-2026-05-26",
    "ecdc-bdbv-drc-uga-2026-05-27",
    "inrb-sitrep-015-2026-05-29",
    "inrb-sitrep-016-2026-05-30",
    "inrb-umie-ebola-drc-2026-build-2026-05-28-bb8b7d5",
    "who-dg-remarks-bdbv-2026-05-20",
    "who-dg-remarks-bdbv-2026-05-22",
    "who-don602-2026-05-15",
    "who-don603-2026-05-21",
    "who-ihr-ec-bdbv-temporary-recommendations-2026-05-22",
    "who-pheic-2026-05-17",
    "wikipedia-2026-ituri-epidemic-2026-05-20"
  ],
  "source_conflict_notes": [
    "Suspected/reported-case count spans 395 (Africa CDC PHECS, 18 May 2026) to 1077 suspected DRC cases (ECDC 27 May 2026, citing 'On 26 May, the Ministry of Health in DRC reported'), the highest valid primary on the latest date. INRB build-2026-05-28 (national_moh, DRC-only restricted GitHub release with data-as-of 26 May) cross-corroborates 1077. The CDC 25 May 906, ECDC 25 May 904, and the DRC MoH all-published-bulletins dashboard aggregate of 854 reported cases (24 May) are retained as dated conflict anchors and not used to down-revise the higher endpoint.",
    "Confirmed deaths reconciled across INRB/INSP/UMIE build-2026-05-28-bb8b7d5 (17 DRC confirmed deaths, national_moh, data-as-of 26 May, DRC-only) and ECDC 27 May (1 Uganda confirmed death) = 18 country-scope confirmed deaths. Suspected deaths reconciled from INRB/INSP/UMIE build-2026-05-28-bb8b7d5 cumul deces suspects (246 DRC). ECDC's 238 suspected DRC deaths on the same data date, CDC 25 May (223), ECDC 25 May (119), Africa CDC PHECS 18 May (106), and the DRC MoH 24 May dashboard aggregate (179) drop to dated conflict anchors. The two series are kept separate per INRB's published schema; the prior cross-class composition that summed suspected and confirmed under one headline is retired.",
    "Confirmed count spans 10 (WHO PHEIC statement, 17 May 2026, case data as of 16 May: 8 Ituri + 2 Kampala; Kinshasa case deconfirmed) to 128 total country-scope confirmed cases (ECDC 27 May 2026, citing DRC MoH 26 May: 121 DRC + 7 Uganda). INRB build-2026-05-28 (DRC-only national_moh) cross-corroborates the DRC component (121). The CDC 25 May 112 (105 DRC + 7 Uganda), ECDC 25 May 101 confirmed, and the DRC MoH 24 May dashboard aggregate of 112 confirmed DRC are retained as dated conflict anchors. CDC and WHO AFRO have not yet published an edition that catches up to the DRC MoH 26 May release.",
    "Spatial model source zones use the INRB-UMIE/INSP per-health-zone series (consortium build-2026-05-28-bb8b7d5, data as of 26 May 2026), which attributes 109 confirmed cases across 18 monitored health zones (11 with confirmed cases). The national DRC and country-scope headline confirmed totals are higher; the difference is carried as unallocated and cross-border attribution-lag context rather than smeared across every source zone. Corridor source load therefore uses the INSP per-health-zone confirmed vector.",
    "CDC 24 May reports five Uganda cases, but does not publish a zone-attributed count table. The DRC MoH dashboard exposes all-published-bulletins aggregate cards and sparse SitRep 009 rows; the aggregate is carried as official count evidence, while the latest sparse rows remain source-review and are not promoted to corridor source load until a cumulative PDF/table label is verified. One American national was evacuated from DRC to Germany and confirmed positive; a high-risk contact was reportedly transferred to Czechia. The reported Kinshasa case was deconfirmed by INRB and is not counted as confirmed.",
    "Per-source archive status: all cited sources are registered in data/bundibugyo-2026/manifest.json. WHO DON 602, WHO PHEIC, WHO DG remarks on 20 and 22 May, WHO IHR temporary recommendations, WHO AFRO landing page, CDC HAN, CDC Current Situation, ECDC May 19/21, and the consensus aggregator are byte-archived with SHA-256; DRC MoH dashboard GraphQL bytes, Africa CDC, Imperial, and PAHO/WHO alert PDF are hash-recorded with restricted raw publisher bytes kept private pending terms or permission confirmation.",
    "INRB SitRep #015 (data cutoff 2026-05-29, published 2026-05-30) promoted the DRC headline tiles: cumul cas confirmes 263, cumul deces parmi confirmes 42, cumul cas suspects 3491, gueris 2. Country-scope confirmed deaths = 42 DRC + 1 UGA (ECDC 27 May) = 43. The cumul deces suspects tile was not included in #015; the 246 value from the prior INRB build (data-as-of 26 May) is carried forward with reason source_schema_evolved.",
    "INRB SitRep #016 (data cutoff 2026-05-30, published 2026-05-31) promoted the refined schema: cumul cas confirmes 282 (with footnote donnees en cours d'harmonisation), cas confirmes actifs 238 (= 282 - 42 deaths - 2 cured), cas suspects en cours d'investigation 220, cas suspects en isolement 101, suspected_active total 321. The cumul deces suspects tile remains absent; the 246 May 26 value is carried forward with reason source_schema_evolved."
  ],
  "visibility": {
    "grade": "low",
    "history_snapshot_count": 0,
    "method_basis": "single_snapshot_bdbv_specific_prior_with_proxy_sensitivity",
    "method_caveat": "No prior daily snapshot series is supplied to Module C for this release; reporting completeness and latency are prior-based, using the Rosello 2015 BDBV Isiro onset-to-notification distribution as the default. This is a historical prior-outbreak estimate, not a fitted 2026 reporting-delay estimate; Camacho 2015 EBOV-Zaire remains the proxy sensitivity comparator.",
    "delay_prior": {
      "label": "Rosello 2015 BDBV Isiro onset-to-notification",
      "gamma_shape_rate": [
        1.1345,
        0.1285
      ],
      "evidence_chain_id": "ec:lovs:grepi:reporting-delay-update:2026-05-23"
    },
    "sensitivity_delay_priors": [
      {
        "label": "Camacho 2015 EBOV-Zaire onset-to-notification sensitivity",
        "gamma_shape_rate": [
          0.81,
          0.18
        ],
        "evidence_chain_id": "ec:lovs:module-c:reporting-delay-priors:2026-05-20"
      }
    ],
    "evidence_chain_ids": [
      "ec:lovs:grepi:reporting-delay-update:2026-05-23",
      "ec:lovs:module-c:reporting-delay-priors:2026-05-20"
    ],
    "reporting_completeness_50": [
      0.49085836786842113,
      0.5712706336969902
    ],
    "publication_latency_50": [
      2.8060481960107864,
      12.414982843836839
    ],
    "confirmation_backlog_50": [
      0,
      0
    ]
  },
  "transmission": {
    "latent_active_chains_95": [
      0,
      2
    ],
    "generations": {
      "1": 0.0,
      "2": 0.0,
      "3": 0.0,
      "4": 0.0,
      "5": 0.012,
      "6": 0.988
    },
    "generations_max_bin_is_censored": true,
    "generations_max_bin_key": "6"
  },
  "corridors": [
    {
      "source": "bunia",
      "target": "nebbi-uga",
      "horizon_days": 30,
      "risk_raw_lower_50": 0.11028173901145094,
      "risk_raw_upper_50": 0.2807272275507473,
      "risk_adj_lower_50": 0.21183927458819443,
      "risk_adj_upper_50": 0.4889576118271988,
      "risk_adj_lower_95": 0.056581547477995854,
      "risk_adj_upper_95": 0.73759211360769,
      "drivers": [
        "zone-attributed confirmed count 36 for this source zone",
        "visibility-adjustment factor 2.04\u00d7 reflects under-reporting in source zone; raw risk likely understates true hazard"
      ]
    },
    {
      "source": "bunia",
      "target": "kasese-uga",
      "horizon_days": 30,
      "risk_raw_lower_50": 0.09927601872680339,
      "risk_raw_upper_50": 0.2626412391867222,
      "risk_adj_lower_50": 0.19184967007197548,
      "risk_adj_upper_50": 0.462437389884103,
      "risk_adj_lower_95": 0.05290211270266524,
      "risk_adj_upper_95": 0.7060057485933424,
      "drivers": [
        "zone-attributed confirmed count 36 for this source zone",
        "visibility-adjustment factor 2.04\u00d7 reflects under-reporting in source zone; raw risk likely understates true hazard"
      ]
    },
    {
      "source": "bunia",
      "target": "bundibugyo-uga",
      "horizon_days": 30,
      "risk_raw_lower_50": 0.09227964884615786,
      "risk_raw_upper_50": 0.26077394694739586,
      "risk_adj_lower_50": 0.17900950166451474,
      "risk_adj_upper_50": 0.45966038840960777,
      "risk_adj_lower_95": 0.05050295207417183,
      "risk_adj_upper_95": 0.7424846795613185,
      "drivers": [
        "zone-attributed confirmed count 36 for this source zone",
        "visibility-adjustment factor 2.04\u00d7 reflects under-reporting in source zone; raw risk likely understates true hazard"
      ]
    },
    {
      "source": "bunia",
      "target": "goma-cod",
      "horizon_days": 30,
      "risk_raw_lower_50": 0.0991497889762141,
      "risk_raw_upper_50": 0.2594110965188864,
      "risk_adj_lower_50": 0.19161901412654436,
      "risk_adj_upper_50": 0.4576289834973488,
      "risk_adj_lower_95": 0.04262964148434711,
      "risk_adj_upper_95": 0.7238509196006881,
      "drivers": [
        "zone-attributed confirmed count 36 for this source zone",
        "visibility-adjustment factor 2.04\u00d7 reflects under-reporting in source zone; raw risk likely understates true hazard"
      ]
    },
    {
      "source": "bunia",
      "target": "kampala-uga",
      "horizon_days": 30,
      "risk_raw_lower_50": 0.09696692303337237,
      "risk_raw_upper_50": 0.2509093895593765,
      "risk_adj_lower_50": 0.18762334355266347,
      "risk_adj_upper_50": 0.44486871633739533,
      "risk_adj_lower_95": 0.05250274756160605,
      "risk_adj_upper_95": 0.7082828440120883,
      "drivers": [
        "zone-attributed confirmed count 36 for this source zone",
        "visibility-adjustment factor 2.04\u00d7 reflects under-reporting in source zone; raw risk likely understates true hazard"
      ]
    },
    {
      "source": "bunia",
      "target": "arua-uga",
      "horizon_days": 30,
      "risk_raw_lower_50": 0.09967017431949143,
      "risk_raw_upper_50": 0.24603237274278497,
      "risk_adj_lower_50": 0.19257006068923616,
      "risk_adj_upper_50": 0.4374810788663882,
      "risk_adj_lower_95": 0.0591894286602639,
      "risk_adj_upper_95": 0.684922288960672,
      "drivers": [
        "zone-attributed confirmed count 36 for this source zone",
        "visibility-adjustment factor 2.04\u00d7 reflects under-reporting in source zone; raw risk likely understates true hazard"
      ]
    },
    {
      "source": "rwampara",
      "target": "arua-uga",
      "horizon_days": 30,
      "risk_raw_lower_50": 0.09518979127094143,
      "risk_raw_upper_50": 0.2430842741421531,
      "risk_adj_lower_50": 0.1843631145129474,
      "risk_adj_upper_50": 0.4329910132687168,
      "risk_adj_lower_95": 0.05057009294419349,
      "risk_adj_upper_95": 0.6592352017088671,
      "drivers": [
        "zone-attributed confirmed count 33 for this source zone",
        "visibility-adjustment factor 2.04\u00d7 reflects under-reporting in source zone; raw risk likely understates true hazard"
      ]
    },
    {
      "source": "bunia",
      "target": "beni-cod",
      "horizon_days": 30,
      "risk_raw_lower_50": 0.09474127553574621,
      "risk_raw_upper_50": 0.2379012133217938,
      "risk_adj_lower_50": 0.18353916269408463,
      "risk_adj_upper_50": 0.42505206330711753,
      "risk_adj_lower_95": 0.04739309831692561,
      "risk_adj_upper_95": 0.7176157159654625,
      "drivers": [
        "zone-attributed confirmed count 36 for this source zone",
        "visibility-adjustment factor 2.04\u00d7 reflects under-reporting in source zone; raw risk likely understates true hazard"
      ]
    },
    {
      "source": "rwampara",
      "target": "nebbi-uga",
      "horizon_days": 30,
      "risk_raw_lower_50": 0.09428191824264057,
      "risk_raw_upper_50": 0.236844527147535,
      "risk_adj_lower_50": 0.18269495945356456,
      "risk_adj_upper_50": 0.4234277314611213,
      "risk_adj_lower_95": 0.06323818888391174,
      "risk_adj_upper_95": 0.696528098132208,
      "drivers": [
        "zone-attributed confirmed count 33 for this source zone",
        "visibility-adjustment factor 2.04\u00d7 reflects under-reporting in source zone; raw risk likely understates true hazard"
      ]
    },
    {
      "source": "rwampara",
      "target": "goma-cod",
      "horizon_days": 30,
      "risk_raw_lower_50": 0.08894099736956015,
      "risk_raw_upper_50": 0.2353959960821443,
      "risk_adj_lower_50": 0.17284630239980714,
      "risk_adj_upper_50": 0.42119531211726435,
      "risk_adj_lower_95": 0.05544751845064857,
      "risk_adj_upper_95": 0.6765128555677616,
      "drivers": [
        "zone-attributed confirmed count 33 for this source zone",
        "visibility-adjustment factor 2.04\u00d7 reflects under-reporting in source zone; raw risk likely understates true hazard"
      ]
    },
    {
      "source": "rwampara",
      "target": "kampala-uga",
      "horizon_days": 30,
      "risk_raw_lower_50": 0.09006239587035211,
      "risk_raw_upper_50": 0.2289801750314641,
      "risk_adj_lower_50": 0.17491905763751298,
      "risk_adj_upper_50": 0.4112581668362904,
      "risk_adj_lower_95": 0.042639650249209064,
      "risk_adj_upper_95": 0.6709285813664575,
      "drivers": [
        "zone-attributed confirmed count 33 for this source zone",
        "visibility-adjustment factor 2.04\u00d7 reflects under-reporting in source zone; raw risk likely understates true hazard"
      ]
    },
    {
      "source": "rwampara",
      "target": "beni-cod",
      "horizon_days": 30,
      "risk_raw_lower_50": 0.08772820048342178,
      "risk_raw_upper_50": 0.22502258286929022,
      "risk_adj_lower_50": 0.1706015350463659,
      "risk_adj_upper_50": 0.40508492867100265,
      "risk_adj_lower_95": 0.039106046675671066,
      "risk_adj_upper_95": 0.6363024050253195,
      "drivers": [
        "zone-attributed confirmed count 33 for this source zone",
        "visibility-adjustment factor 2.04\u00d7 reflects under-reporting in source zone; raw risk likely understates true hazard"
      ]
    },
    {
      "source": "rwampara",
      "target": "bundibugyo-uga",
      "horizon_days": 30,
      "risk_raw_lower_50": 0.08889774025537542,
      "risk_raw_upper_50": 0.22487097011206453,
      "risk_adj_lower_50": 0.1727650264380924,
      "risk_adj_upper_50": 0.4048485089892068,
      "risk_adj_lower_95": 0.059265351077679156,
      "risk_adj_upper_95": 0.6686577903907468,
      "drivers": [
        "zone-attributed confirmed count 33 for this source zone",
        "visibility-adjustment factor 2.04\u00d7 reflects under-reporting in source zone; raw risk likely understates true hazard"
      ]
    },
    {
      "source": "rwampara",
      "target": "kasese-uga",
      "horizon_days": 30,
      "risk_raw_lower_50": 0.08093985379217589,
      "risk_raw_upper_50": 0.22320303342270315,
      "risk_adj_lower_50": 0.1579794572815058,
      "risk_adj_upper_50": 0.4022363869323167,
      "risk_adj_lower_95": 0.04539262592473755,
      "risk_adj_upper_95": 0.6817123688955368,
      "drivers": [
        "zone-attributed confirmed count 33 for this source zone",
        "visibility-adjustment factor 2.04\u00d7 reflects under-reporting in source zone; raw risk likely understates true hazard"
      ]
    },
    {
      "source": "mongbwalu",
      "target": "arua-uga",
      "horizon_days": 30,
      "risk_raw_lower_50": 0.057707959168929845,
      "risk_raw_upper_50": 0.1533334825744827,
      "risk_adj_lower_50": 0.11404890700125073,
      "risk_adj_upper_50": 0.287585877536499,
      "risk_adj_lower_95": 0.0332455388521283,
      "risk_adj_upper_95": 0.4559121496659428,
      "drivers": [
        "zone-attributed confirmed count 20 for this source zone",
        "visibility-adjustment factor 2.04\u00d7 reflects under-reporting in source zone; raw risk likely understates true hazard"
      ]
    },
    {
      "source": "mongbwalu",
      "target": "kasese-uga",
      "horizon_days": 30,
      "risk_raw_lower_50": 0.05982827306017019,
      "risk_raw_upper_50": 0.15221799271054337,
      "risk_adj_lower_50": 0.1181059571656835,
      "risk_adj_upper_50": 0.28567272506289254,
      "risk_adj_lower_95": 0.031310347441212,
      "risk_adj_upper_95": 0.5058044995336014,
      "drivers": [
        "zone-attributed confirmed count 20 for this source zone",
        "visibility-adjustment factor 2.04\u00d7 reflects under-reporting in source zone; raw risk likely understates true hazard"
      ]
    },
    {
      "source": "mongbwalu",
      "target": "goma-cod",
      "horizon_days": 30,
      "risk_raw_lower_50": 0.057523280801798304,
      "risk_raw_upper_50": 0.15114949453641513,
      "risk_adj_lower_50": 0.11369559117862557,
      "risk_adj_upper_50": 0.28383752070515444,
      "risk_adj_lower_95": 0.03747863605278815,
      "risk_adj_upper_95": 0.5152483390216205,
      "drivers": [
        "zone-attributed confirmed count 20 for this source zone",
        "visibility-adjustment factor 2.04\u00d7 reflects under-reporting in source zone; raw risk likely understates true hazard"
      ]
    },
    {
      "source": "mongbwalu",
      "target": "nebbi-uga",
      "horizon_days": 30,
      "risk_raw_lower_50": 0.05356873989799904,
      "risk_raw_upper_50": 0.1511428947218616,
      "risk_adj_lower_50": 0.10610289690983418,
      "risk_adj_upper_50": 0.2838261774500722,
      "risk_adj_lower_95": 0.03691036759574853,
      "risk_adj_upper_95": 0.49429475132305356,
      "drivers": [
        "zone-attributed confirmed count 20 for this source zone",
        "visibility-adjustment factor 2.04\u00d7 reflects under-reporting in source zone; raw risk likely understates true hazard"
      ]
    },
    {
      "source": "mongbwalu",
      "target": "kampala-uga",
      "horizon_days": 30,
      "risk_raw_lower_50": 0.05550726382442739,
      "risk_raw_upper_50": 0.15088090522319883,
      "risk_adj_lower_50": 0.10982878856806497,
      "risk_adj_upper_50": 0.28337579943036056,
      "risk_adj_lower_95": 0.03838205350735018,
      "risk_adj_upper_95": 0.4868235027826315,
      "drivers": [
        "zone-attributed confirmed count 20 for this source zone",
        "visibility-adjustment factor 2.04\u00d7 reflects under-reporting in source zone; raw risk likely understates true hazard"
      ]
    },
    {
      "source": "mongbwalu",
      "target": "beni-cod",
      "horizon_days": 30,
      "risk_raw_lower_50": 0.05526257585243233,
      "risk_raw_upper_50": 0.14422364024482331,
      "risk_adj_lower_50": 0.1093590605790867,
      "risk_adj_upper_50": 0.27188289927617526,
      "risk_adj_lower_95": 0.03522332805375611,
      "risk_adj_upper_95": 0.46401577154886836,
      "drivers": [
        "zone-attributed confirmed count 20 for this source zone",
        "visibility-adjustment factor 2.04\u00d7 reflects under-reporting in source zone; raw risk likely understates true hazard"
      ]
    },
    {
      "source": "mongbwalu",
      "target": "bundibugyo-uga",
      "horizon_days": 30,
      "risk_raw_lower_50": 0.0585013570863446,
      "risk_raw_upper_50": 0.14399995752788056,
      "risk_adj_lower_50": 0.11556840977187521,
      "risk_adj_upper_50": 0.27149518082690083,
      "risk_adj_lower_95": 0.03065461804657245,
      "risk_adj_upper_95": 0.5162424578997203,
      "drivers": [
        "zone-attributed confirmed count 20 for this source zone",
        "visibility-adjustment factor 2.04\u00d7 reflects under-reporting in source zone; raw risk likely understates true hazard"
      ]
    },
    {
      "source": "nyankunde",
      "target": "kampala-uga",
      "horizon_days": 30,
      "risk_raw_lower_50": 0.028004718338710266,
      "risk_raw_upper_50": 0.07991391908287723,
      "risk_adj_lower_50": 0.056224205061771254,
      "risk_adj_upper_50": 0.15606359623632518,
      "risk_adj_lower_95": 0.015066368254891918,
      "risk_adj_upper_95": 0.3030343200037626,
      "drivers": [
        "zone-attributed confirmed count 10 for this source zone",
        "visibility-adjustment factor 2.04\u00d7 reflects under-reporting in source zone; raw risk likely understates true hazard"
      ]
    },
    {
      "source": "nyankunde",
      "target": "goma-cod",
      "horizon_days": 30,
      "risk_raw_lower_50": 0.031303709175569044,
      "risk_raw_upper_50": 0.07915509245384203,
      "risk_adj_lower_50": 0.0627384578848498,
      "risk_adj_upper_50": 0.15464521235604528,
      "risk_adj_lower_95": 0.013666119919448858,
      "risk_adj_upper_95": 0.28937624109572674,
      "drivers": [
        "zone-attributed confirmed count 10 for this source zone",
        "visibility-adjustment factor 2.04\u00d7 reflects under-reporting in source zone; raw risk likely understates true hazard"
      ]
    },
    {
      "source": "nyankunde",
      "target": "kasese-uga",
      "horizon_days": 30,
      "risk_raw_lower_50": 0.030230549896192976,
      "risk_raw_upper_50": 0.07900317624945707,
      "risk_adj_lower_50": 0.06062189823718861,
      "risk_adj_upper_50": 0.15436105891396337,
      "risk_adj_lower_95": 0.015927689771455526,
      "risk_adj_upper_95": 0.2909811990639095,
      "drivers": [
        "zone-attributed confirmed count 10 for this source zone",
        "visibility-adjustment factor 2.04\u00d7 reflects under-reporting in source zone; raw risk likely understates true hazard"
      ]
    },
    {
      "source": "nyankunde",
      "target": "bundibugyo-uga",
      "horizon_days": 30,
      "risk_raw_lower_50": 0.030034897487597773,
      "risk_raw_upper_50": 0.07633165581126983,
      "risk_adj_lower_50": 0.0602357566611631,
      "risk_adj_upper_50": 0.149356235306918,
      "risk_adj_lower_95": 0.017884036273501255,
      "risk_adj_upper_95": 0.2847323178534088,
      "drivers": [
        "zone-attributed confirmed count 10 for this source zone",
        "visibility-adjustment factor 2.04\u00d7 reflects under-reporting in source zone; raw risk likely understates true hazard"
      ]
    },
    {
      "source": "nyankunde",
      "target": "arua-uga",
      "horizon_days": 30,
      "risk_raw_lower_50": 0.030328283893373498,
      "risk_raw_upper_50": 0.07562156929692423,
      "risk_adj_lower_50": 0.06081475506998352,
      "risk_adj_upper_50": 0.148023537856127,
      "risk_adj_lower_95": 0.01328757411656801,
      "risk_adj_upper_95": 0.2854115905162654,
      "drivers": [
        "zone-attributed confirmed count 10 for this source zone",
        "visibility-adjustment factor 2.04\u00d7 reflects under-reporting in source zone; raw risk likely understates true hazard"
      ]
    },
    {
      "source": "nyankunde",
      "target": "beni-cod",
      "horizon_days": 30,
      "risk_raw_lower_50": 0.028411325171645296,
      "risk_raw_upper_50": 0.07508389065575966,
      "risk_adj_lower_50": 0.05702834222503253,
      "risk_adj_upper_50": 0.14701364457849492,
      "risk_adj_lower_95": 0.013369243176544532,
      "risk_adj_upper_95": 0.2596164707949314,
      "drivers": [
        "zone-attributed confirmed count 10 for this source zone",
        "visibility-adjustment factor 2.04\u00d7 reflects under-reporting in source zone; raw risk likely understates true hazard"
      ]
    },
    {
      "source": "nyankunde",
      "target": "nebbi-uga",
      "horizon_days": 30,
      "risk_raw_lower_50": 0.02933544198962254,
      "risk_raw_upper_50": 0.07353599031943711,
      "risk_adj_lower_50": 0.05885463190309098,
      "risk_adj_upper_50": 0.14410283682163652,
      "risk_adj_lower_95": 0.012600397120207288,
      "risk_adj_upper_95": 0.27658720869059544,
      "drivers": [
        "zone-attributed confirmed count 10 for this source zone",
        "visibility-adjustment factor 2.04\u00d7 reflects under-reporting in source zone; raw risk likely understates true hazard"
      ]
    },
    {
      "source": "butembo",
      "target": "beni-cod",
      "horizon_days": 30,
      "risk_raw_lower_50": 0.009426364088773814,
      "risk_raw_upper_50": 0.024961836757234263,
      "risk_adj_lower_50": 0.019109965081628877,
      "risk_adj_upper_50": 0.05019528864555531,
      "risk_adj_lower_95": 0.0049140817627296,
      "risk_adj_upper_95": 0.09423522739854281,
      "drivers": [
        "zone-attributed confirmed count 3 for this source zone",
        "visibility-adjustment factor 2.04\u00d7 reflects under-reporting in source zone; raw risk likely understates true hazard"
      ]
    },
    {
      "source": "butembo",
      "target": "goma-cod",
      "horizon_days": 30,
      "risk_raw_lower_50": 0.00883751012949835,
      "risk_raw_upper_50": 0.024622974005967302,
      "risk_adj_lower_50": 0.017921685071076415,
      "risk_adj_upper_50": 0.049522703856868244,
      "risk_adj_lower_95": 0.005472892406678373,
      "risk_adj_upper_95": 0.0930381422374211,
      "drivers": [
        "zone-attributed confirmed count 3 for this source zone",
        "visibility-adjustment factor 2.04\u00d7 reflects under-reporting in source zone; raw risk likely understates true hazard"
      ]
    },
    {
      "source": "butembo",
      "target": "arua-uga",
      "horizon_days": 30,
      "risk_raw_lower_50": 0.008296362378555772,
      "risk_raw_upper_50": 0.024230991346749525,
      "risk_adj_lower_50": 0.01682902831140448,
      "risk_adj_upper_50": 0.04874436218022063,
      "risk_adj_lower_95": 0.004313472019797893,
      "risk_adj_upper_95": 0.09470341002560421,
      "drivers": [
        "zone-attributed confirmed count 3 for this source zone",
        "visibility-adjustment factor 2.04\u00d7 reflects under-reporting in source zone; raw risk likely understates true hazard"
      ]
    },
    {
      "source": "butembo",
      "target": "nebbi-uga",
      "horizon_days": 30,
      "risk_raw_lower_50": 0.008426608878335712,
      "risk_raw_upper_50": 0.02397049145330546,
      "risk_adj_lower_50": 0.017092069926619713,
      "risk_adj_upper_50": 0.04822691958026043,
      "risk_adj_lower_95": 0.004647366508994039,
      "risk_adj_upper_95": 0.08966314033520172,
      "drivers": [
        "zone-attributed confirmed count 3 for this source zone",
        "visibility-adjustment factor 2.04\u00d7 reflects under-reporting in source zone; raw risk likely understates true hazard"
      ]
    },
    {
      "source": "butembo",
      "target": "bundibugyo-uga",
      "horizon_days": 30,
      "risk_raw_lower_50": 0.00829565442428129,
      "risk_raw_upper_50": 0.02308635596614808,
      "risk_adj_lower_50": 0.016827597564066432,
      "risk_adj_upper_50": 0.04646965580951376,
      "risk_adj_lower_95": 0.004256891973758456,
      "risk_adj_upper_95": 0.10405862271123907,
      "drivers": [
        "zone-attributed confirmed count 3 for this source zone",
        "visibility-adjustment factor 2.04\u00d7 reflects under-reporting in source zone; raw risk likely understates true hazard"
      ]
    },
    {
      "source": "butembo",
      "target": "kasese-uga",
      "horizon_days": 30,
      "risk_raw_lower_50": 0.008634626960480563,
      "risk_raw_upper_50": 0.022811502302159836,
      "risk_adj_lower_50": 0.017512106801842148,
      "risk_adj_upper_50": 0.04592301680108457,
      "risk_adj_lower_95": 0.004296025518576591,
      "risk_adj_upper_95": 0.08970642744398172,
      "drivers": [
        "zone-attributed confirmed count 3 for this source zone",
        "visibility-adjustment factor 2.04\u00d7 reflects under-reporting in source zone; raw risk likely understates true hazard"
      ]
    },
    {
      "source": "butembo",
      "target": "kampala-uga",
      "horizon_days": 30,
      "risk_raw_lower_50": 0.007952173678942437,
      "risk_raw_upper_50": 0.021803349847224873,
      "risk_adj_lower_50": 0.01613373866370224,
      "risk_adj_upper_50": 0.04391667962837642,
      "risk_adj_lower_95": 0.0048777997874523095,
      "risk_adj_upper_95": 0.08546183369300514,
      "drivers": [
        "zone-attributed confirmed count 3 for this source zone",
        "visibility-adjustment factor 2.04\u00d7 reflects under-reporting in source zone; raw risk likely understates true hazard"
      ]
    },
    {
      "source": "nizi",
      "target": "goma-cod",
      "horizon_days": 30,
      "risk_raw_lower_50": 0.005788610612346534,
      "risk_raw_upper_50": 0.016892908070466867,
      "risk_adj_lower_50": 0.011757431148024938,
      "risk_adj_upper_50": 0.03411358585743987,
      "risk_adj_lower_95": 0.0034033310107786678,
      "risk_adj_upper_95": 0.06994107669284519,
      "drivers": [
        "zone-attributed confirmed count 2 for this source zone",
        "visibility-adjustment factor 2.04\u00d7 reflects under-reporting in source zone; raw risk likely understates true hazard"
      ]
    },
    {
      "source": "nizi",
      "target": "arua-uga",
      "horizon_days": 30,
      "risk_raw_lower_50": 0.0060103265680337414,
      "risk_raw_upper_50": 0.016466147102952078,
      "risk_adj_lower_50": 0.012206358245422322,
      "risk_adj_upper_50": 0.033259205224863225,
      "risk_adj_lower_95": 0.003668531062091096,
      "risk_adj_upper_95": 0.07016268859398056,
      "drivers": [
        "zone-attributed confirmed count 2 for this source zone",
        "visibility-adjustment factor 2.04\u00d7 reflects under-reporting in source zone; raw risk likely understates true hazard"
      ]
    },
    {
      "source": "nizi",
      "target": "nebbi-uga",
      "horizon_days": 30,
      "risk_raw_lower_50": 0.00585815680787638,
      "risk_raw_upper_50": 0.016124502039110145,
      "risk_adj_lower_50": 0.01189825885847462,
      "risk_adj_upper_50": 0.03257494969227254,
      "risk_adj_lower_95": 0.002512719415321177,
      "risk_adj_upper_95": 0.07575910545511216,
      "drivers": [
        "zone-attributed confirmed count 2 for this source zone",
        "visibility-adjustment factor 2.04\u00d7 reflects under-reporting in source zone; raw risk likely understates true hazard"
      ]
    },
    {
      "source": "nizi",
      "target": "bundibugyo-uga",
      "horizon_days": 30,
      "risk_raw_lower_50": 0.005497131386792642,
      "risk_raw_upper_50": 0.01609627655254245,
      "risk_adj_lower_50": 0.01116709096034027,
      "risk_adj_upper_50": 0.03251840908601705,
      "risk_adj_lower_95": 0.0023336707778518124,
      "risk_adj_upper_95": 0.06384374756961507,
      "drivers": [
        "zone-attributed confirmed count 2 for this source zone",
        "visibility-adjustment factor 2.04\u00d7 reflects under-reporting in source zone; raw risk likely understates true hazard"
      ]
    },
    {
      "source": "nizi",
      "target": "kampala-uga",
      "horizon_days": 30,
      "risk_raw_lower_50": 0.0053329036099907245,
      "risk_raw_upper_50": 0.01562643249777379,
      "risk_adj_lower_50": 0.010834398152007457,
      "risk_adj_upper_50": 0.03157696297549545,
      "risk_adj_lower_95": 0.0024231387775072778,
      "risk_adj_upper_95": 0.06556412764144093,
      "drivers": [
        "zone-attributed confirmed count 2 for this source zone",
        "visibility-adjustment factor 2.04\u00d7 reflects under-reporting in source zone; raw risk likely understates true hazard"
      ]
    },
    {
      "source": "nizi",
      "target": "kasese-uga",
      "horizon_days": 30,
      "risk_raw_lower_50": 0.005349452582764841,
      "risk_raw_upper_50": 0.01550715941624628,
      "risk_adj_lower_50": 0.010867925755516816,
      "risk_adj_upper_50": 0.03133789643032339,
      "risk_adj_lower_95": 0.002271393482270895,
      "risk_adj_upper_95": 0.06804114011908857,
      "drivers": [
        "zone-attributed confirmed count 2 for this source zone",
        "visibility-adjustment factor 2.04\u00d7 reflects under-reporting in source zone; raw risk likely understates true hazard"
      ]
    },
    {
      "source": "nizi",
      "target": "beni-cod",
      "horizon_days": 30,
      "risk_raw_lower_50": 0.0058538094529925755,
      "risk_raw_upper_50": 0.014753211652452858,
      "risk_adj_lower_50": 0.011889455939891547,
      "risk_adj_upper_50": 0.02982601727783582,
      "risk_adj_lower_95": 0.0028242759023123704,
      "risk_adj_upper_95": 0.05956713078668124,
      "drivers": [
        "zone-attributed confirmed count 2 for this source zone",
        "visibility-adjustment factor 2.04\u00d7 reflects under-reporting in source zone; raw risk likely understates true hazard"
      ]
    },
    {
      "source": "goma-cod",
      "target": "arua-uga",
      "horizon_days": 30,
      "risk_raw_lower_50": 0.0030179856868135513,
      "risk_raw_upper_50": 0.008661368535915842,
      "risk_adj_lower_50": 0.006138760787313957,
      "risk_adj_upper_50": 0.01756609746001228,
      "risk_adj_lower_95": 0.0015186529488979588,
      "risk_adj_upper_95": 0.03365792553415829,
      "drivers": [
        "zone-attributed confirmed count 1 for this source zone",
        "visibility-adjustment factor 2.04\u00d7 reflects under-reporting in source zone; raw risk likely understates true hazard"
      ]
    },
    {
      "source": "oicha",
      "target": "bundibugyo-uga",
      "horizon_days": 30,
      "risk_raw_lower_50": 0.0030341000143697117,
      "risk_raw_upper_50": 0.00846253617771503,
      "risk_adj_lower_50": 0.00617148658012262,
      "risk_adj_upper_50": 0.01716462354130302,
      "risk_adj_lower_95": 0.0017786093778454444,
      "risk_adj_upper_95": 0.034362598537985775,
      "drivers": [
        "zone-attributed confirmed count 1 for this source zone",
        "visibility-adjustment factor 2.04\u00d7 reflects under-reporting in source zone; raw risk likely understates true hazard"
      ]
    },
    {
      "source": "oicha",
      "target": "nebbi-uga",
      "horizon_days": 30,
      "risk_raw_lower_50": 0.002831677945587252,
      "risk_raw_upper_50": 0.00843034087107808,
      "risk_adj_lower_50": 0.005760357251983594,
      "risk_adj_upper_50": 0.017099608265996297,
      "risk_adj_lower_95": 0.0013547423301941224,
      "risk_adj_upper_95": 0.03258999649109458,
      "drivers": [
        "zone-attributed confirmed count 1 for this source zone",
        "visibility-adjustment factor 2.04\u00d7 reflects under-reporting in source zone; raw risk likely understates true hazard"
      ]
    },
    {
      "source": "oicha",
      "target": "kampala-uga",
      "horizon_days": 30,
      "risk_raw_lower_50": 0.0031476470731165163,
      "risk_raw_upper_50": 0.008352534440049214,
      "risk_adj_lower_50": 0.006402068540273725,
      "risk_adj_upper_50": 0.01694247627928583,
      "risk_adj_lower_95": 0.0014001169478748024,
      "risk_adj_upper_95": 0.03341357042820716,
      "drivers": [
        "zone-attributed confirmed count 1 for this source zone",
        "visibility-adjustment factor 2.04\u00d7 reflects under-reporting in source zone; raw risk likely understates true hazard"
      ]
    },
    {
      "source": "aru",
      "target": "bundibugyo-uga",
      "horizon_days": 30,
      "risk_raw_lower_50": 0.0027324897798243486,
      "risk_raw_upper_50": 0.008346425227446497,
      "risk_adj_lower_50": 0.005558869371467934,
      "risk_adj_upper_50": 0.01693013808229582,
      "risk_adj_lower_95": 0.0015895377369067184,
      "risk_adj_upper_95": 0.03457244449720674,
      "drivers": [
        "zone-attributed confirmed count 1 for this source zone",
        "visibility-adjustment factor 2.04\u00d7 reflects under-reporting in source zone; raw risk likely understates true hazard"
      ]
    },
    {
      "source": "aru",
      "target": "nebbi-uga",
      "horizon_days": 30,
      "risk_raw_lower_50": 0.0030554462005819294,
      "risk_raw_upper_50": 0.008253366684756458,
      "risk_adj_lower_50": 0.006214833961396993,
      "risk_adj_upper_50": 0.016742186789901053,
      "risk_adj_lower_95": 0.0013916593520372227,
      "risk_adj_upper_95": 0.03464250398519684,
      "drivers": [
        "zone-attributed confirmed count 1 for this source zone",
        "visibility-adjustment factor 2.04\u00d7 reflects under-reporting in source zone; raw risk likely understates true hazard"
      ]
    },
    {
      "source": "miti-murhesa",
      "target": "kasese-uga",
      "horizon_days": 30,
      "risk_raw_lower_50": 0.0027521196763170275,
      "risk_raw_upper_50": 0.008253007416919561,
      "risk_adj_lower_50": 0.005598746704830765,
      "risk_adj_upper_50": 0.016741461470649283,
      "risk_adj_lower_95": 0.0016434603433788497,
      "risk_adj_upper_95": 0.0339072098945655,
      "drivers": [
        "zone-attributed confirmed count 1 for this source zone",
        "visibility-adjustment factor 2.04\u00d7 reflects under-reporting in source zone; raw risk likely understates true hazard"
      ]
    },
    {
      "source": "kilo",
      "target": "beni-cod",
      "horizon_days": 30,
      "risk_raw_lower_50": 0.0025914993361856042,
      "risk_raw_upper_50": 0.008193028692882742,
      "risk_adj_lower_50": 0.0052724299750311066,
      "risk_adj_upper_50": 0.01662030890164007,
      "risk_adj_lower_95": 0.001768964565313061,
      "risk_adj_upper_95": 0.03449862237167078,
      "drivers": [
        "zone-attributed confirmed count 1 for this source zone",
        "visibility-adjustment factor 2.04\u00d7 reflects under-reporting in source zone; raw risk likely understates true hazard"
      ]
    },
    {
      "source": "miti-murhesa",
      "target": "kampala-uga",
      "horizon_days": 30,
      "risk_raw_lower_50": 0.0025525861522541216,
      "risk_raw_upper_50": 0.008152138795012476,
      "risk_adj_lower_50": 0.005193365789894516,
      "risk_adj_upper_50": 0.01653771524920092,
      "risk_adj_lower_95": 0.001048224858606453,
      "risk_adj_upper_95": 0.0331806680911467,
      "drivers": [
        "zone-attributed confirmed count 1 for this source zone",
        "visibility-adjustment factor 2.04\u00d7 reflects under-reporting in source zone; raw risk likely understates true hazard"
      ]
    },
    {
      "source": "miti-murhesa",
      "target": "goma-cod",
      "horizon_days": 30,
      "risk_raw_lower_50": 0.0029935294616419417,
      "risk_raw_upper_50": 0.008136996191470264,
      "risk_adj_lower_50": 0.0060890927265427885,
      "risk_adj_upper_50": 0.016507126453923077,
      "risk_adj_lower_95": 0.0014386023269028362,
      "risk_adj_upper_95": 0.038150562046520446,
      "drivers": [
        "zone-attributed confirmed count 1 for this source zone",
        "visibility-adjustment factor 2.04\u00d7 reflects under-reporting in source zone; raw risk likely understates true hazard"
      ]
    },
    {
      "source": "goma-cod",
      "target": "nebbi-uga",
      "horizon_days": 30,
      "risk_raw_lower_50": 0.003041892506657845,
      "risk_raw_upper_50": 0.008132314230514998,
      "risk_adj_lower_50": 0.006187311779522253,
      "risk_adj_upper_50": 0.016497668735587168,
      "risk_adj_lower_95": 0.001600805062568661,
      "risk_adj_upper_95": 0.031598558506402426,
      "drivers": [
        "zone-attributed confirmed count 1 for this source zone",
        "visibility-adjustment factor 2.04\u00d7 reflects under-reporting in source zone; raw risk likely understates true hazard"
      ]
    },
    {
      "source": "oicha",
      "target": "goma-cod",
      "horizon_days": 30,
      "risk_raw_lower_50": 0.002964052942423162,
      "risk_raw_upper_50": 0.008114990185431659,
      "risk_adj_lower_50": 0.0060292273139373465,
      "risk_adj_upper_50": 0.016462671968745846,
      "risk_adj_lower_95": 0.0019065201422840906,
      "risk_adj_upper_95": 0.03497051817647589,
      "drivers": [
        "zone-attributed confirmed count 1 for this source zone",
        "visibility-adjustment factor 2.04\u00d7 reflects under-reporting in source zone; raw risk likely understates true hazard"
      ]
    },
    {
      "source": "aru",
      "target": "kasese-uga",
      "horizon_days": 30,
      "risk_raw_lower_50": 0.0027319774677898867,
      "risk_raw_upper_50": 0.008082895604778845,
      "risk_adj_lower_50": 0.005557828735669346,
      "risk_adj_upper_50": 0.016397837147125033,
      "risk_adj_lower_95": 0.0013412868516377743,
      "risk_adj_upper_95": 0.03420456852399703,
      "drivers": [
        "zone-attributed confirmed count 1 for this source zone",
        "visibility-adjustment factor 2.04\u00d7 reflects under-reporting in source zone; raw risk likely understates true hazard"
      ]
    },
    {
      "source": "aru",
      "target": "goma-cod",
      "horizon_days": 30,
      "risk_raw_lower_50": 0.0029067078909233712,
      "risk_raw_upper_50": 0.00807833892754814,
      "risk_adj_lower_50": 0.005912756858873713,
      "risk_adj_upper_50": 0.01638863201618604,
      "risk_adj_lower_95": 0.0017981025783083526,
      "risk_adj_upper_95": 0.03234082740027106,
      "drivers": [
        "zone-attributed confirmed count 1 for this source zone",
        "visibility-adjustment factor 2.04\u00d7 reflects under-reporting in source zone; raw risk likely understates true hazard"
      ]
    },
    {
      "source": "aru",
      "target": "beni-cod",
      "horizon_days": 30,
      "risk_raw_lower_50": 0.002794166575963458,
      "risk_raw_upper_50": 0.008059236574209983,
      "risk_adj_lower_50": 0.005684160239478014,
      "risk_adj_upper_50": 0.016350041440613416,
      "risk_adj_lower_95": 0.0017158613989549988,
      "risk_adj_upper_95": 0.035783099392809894,
      "drivers": [
        "zone-attributed confirmed count 1 for this source zone",
        "visibility-adjustment factor 2.04\u00d7 reflects under-reporting in source zone; raw risk likely understates true hazard"
      ]
    },
    {
      "source": "oicha",
      "target": "beni-cod",
      "horizon_days": 30,
      "risk_raw_lower_50": 0.0026358806818985725,
      "risk_raw_upper_50": 0.008053995509786638,
      "risk_adj_lower_50": 0.005362600787499255,
      "risk_adj_upper_50": 0.016339453328409526,
      "risk_adj_lower_95": 0.0015864756927545412,
      "risk_adj_upper_95": 0.037985172353673706,
      "drivers": [
        "zone-attributed confirmed count 1 for this source zone",
        "visibility-adjustment factor 2.04\u00d7 reflects under-reporting in source zone; raw risk likely understates true hazard"
      ]
    },
    {
      "source": "oicha",
      "target": "arua-uga",
      "horizon_days": 30,
      "risk_raw_lower_50": 0.002990915574877989,
      "risk_raw_upper_50": 0.008031128117398423,
      "risk_adj_lower_50": 0.006083784148794347,
      "risk_adj_upper_50": 0.016293252628029664,
      "risk_adj_lower_95": 0.0014790173799074965,
      "risk_adj_upper_95": 0.030308851716050474,
      "drivers": [
        "zone-attributed confirmed count 1 for this source zone",
        "visibility-adjustment factor 2.04\u00d7 reflects under-reporting in source zone; raw risk likely understates true hazard"
      ]
    },
    {
      "source": "kilo",
      "target": "arua-uga",
      "horizon_days": 30,
      "risk_raw_lower_50": 0.003044952712381671,
      "risk_raw_upper_50": 0.008026459642557549,
      "risk_adj_lower_50": 0.006193526575142855,
      "risk_adj_upper_50": 0.016283823715768725,
      "risk_adj_lower_95": 0.001408799904485267,
      "risk_adj_upper_95": 0.03119312901939627,
      "drivers": [
        "zone-attributed confirmed count 1 for this source zone",
        "visibility-adjustment factor 2.04\u00d7 reflects under-reporting in source zone; raw risk likely understates true hazard"
      ]
    },
    {
      "source": "aru",
      "target": "arua-uga",
      "horizon_days": 30,
      "risk_raw_lower_50": 0.0027422631235332895,
      "risk_raw_upper_50": 0.008025043368809714,
      "risk_adj_lower_50": 0.005578723657733126,
      "risk_adj_upper_50": 0.01628096233682172,
      "risk_adj_lower_95": 0.001262660851748798,
      "risk_adj_upper_95": 0.03243565996611213,
      "drivers": [
        "zone-attributed confirmed count 1 for this source zone",
        "visibility-adjustment factor 2.04\u00d7 reflects under-reporting in source zone; raw risk likely understates true hazard"
      ]
    },
    {
      "source": "oicha",
      "target": "kasese-uga",
      "horizon_days": 30,
      "risk_raw_lower_50": 0.0027063365194242295,
      "risk_raw_upper_50": 0.007982985437292783,
      "risk_adj_lower_50": 0.005505739096723167,
      "risk_adj_upper_50": 0.016195990152269635,
      "risk_adj_lower_95": 0.001352210208695584,
      "risk_adj_upper_95": 0.03223180824757393,
      "drivers": [
        "zone-attributed confirmed count 1 for this source zone",
        "visibility-adjustment factor 2.04\u00d7 reflects under-reporting in source zone; raw risk likely understates true hazard"
      ]
    },
    {
      "source": "goma-cod",
      "target": "bundibugyo-uga",
      "horizon_days": 30,
      "risk_raw_lower_50": 0.0028613268238068257,
      "risk_raw_upper_50": 0.007964756178920201,
      "risk_adj_lower_50": 0.005820581025319738,
      "risk_adj_upper_50": 0.016159160859246735,
      "risk_adj_lower_95": 0.001076574179632972,
      "risk_adj_upper_95": 0.037152225109460625,
      "drivers": [
        "zone-attributed confirmed count 1 for this source zone",
        "visibility-adjustment factor 2.04\u00d7 reflects under-reporting in source zone; raw risk likely understates true hazard"
      ]
    },
    {
      "source": "miti-murhesa",
      "target": "beni-cod",
      "horizon_days": 30,
      "risk_raw_lower_50": 0.002607775567383175,
      "risk_raw_upper_50": 0.007939187193843983,
      "risk_adj_lower_50": 0.00530549940705341,
      "risk_adj_upper_50": 0.016107500008654574,
      "risk_adj_lower_95": 0.001505169199406284,
      "risk_adj_upper_95": 0.035134246832987014,
      "drivers": [
        "zone-attributed confirmed count 1 for this source zone",
        "visibility-adjustment factor 2.04\u00d7 reflects under-reporting in source zone; raw risk likely understates true hazard"
      ]
    },
    {
      "source": "goma-cod",
      "target": "kampala-uga",
      "horizon_days": 30,
      "risk_raw_lower_50": 0.0028164656331642612,
      "risk_raw_upper_50": 0.007863182096834898,
      "risk_adj_lower_50": 0.005729456762595092,
      "risk_adj_upper_50": 0.015953927474969626,
      "risk_adj_lower_95": 0.0010099932451804183,
      "risk_adj_upper_95": 0.03426824855346419,
      "drivers": [
        "zone-attributed confirmed count 1 for this source zone",
        "visibility-adjustment factor 2.04\u00d7 reflects under-reporting in source zone; raw risk likely understates true hazard"
      ]
    },
    {
      "source": "kilo",
      "target": "nebbi-uga",
      "horizon_days": 30,
      "risk_raw_lower_50": 0.0028020893989045836,
      "risk_raw_upper_50": 0.007842567437174958,
      "risk_adj_lower_50": 0.005700254173009733,
      "risk_adj_upper_50": 0.015912272397712757,
      "risk_adj_lower_95": 0.001526339036524857,
      "risk_adj_upper_95": 0.03143861710868351,
      "drivers": [
        "zone-attributed confirmed count 1 for this source zone",
        "visibility-adjustment factor 2.04\u00d7 reflects under-reporting in source zone; raw risk likely understates true hazard"
      ]
    },
    {
      "source": "miti-murhesa",
      "target": "arua-uga",
      "horizon_days": 30,
      "risk_raw_lower_50": 0.002929234120899321,
      "risk_raw_upper_50": 0.007809431666885275,
      "risk_adj_lower_50": 0.0059585095096705565,
      "risk_adj_upper_50": 0.01584531370216863,
      "risk_adj_lower_95": 0.0016940579233380964,
      "risk_adj_upper_95": 0.034059349341980676,
      "drivers": [
        "zone-attributed confirmed count 1 for this source zone",
        "visibility-adjustment factor 2.04\u00d7 reflects under-reporting in source zone; raw risk likely understates true hazard"
      ]
    },
    {
      "source": "miti-murhesa",
      "target": "bundibugyo-uga",
      "horizon_days": 30,
      "risk_raw_lower_50": 0.0026633426362618895,
      "risk_raw_upper_50": 0.007785727408781612,
      "risk_adj_lower_50": 0.005418393836554319,
      "risk_adj_upper_50": 0.01579741379190777,
      "risk_adj_lower_95": 0.0013728821112243496,
      "risk_adj_upper_95": 0.031886692410668674,
      "drivers": [
        "zone-attributed confirmed count 1 for this source zone",
        "visibility-adjustment factor 2.04\u00d7 reflects under-reporting in source zone; raw risk likely understates true hazard"
      ]
    },
    {
      "source": "miti-murhesa",
      "target": "nebbi-uga",
      "horizon_days": 30,
      "risk_raw_lower_50": 0.0029321389340761506,
      "risk_raw_upper_50": 0.007782744586189716,
      "risk_adj_lower_50": 0.0059644093402181075,
      "risk_adj_upper_50": 0.01579138555820092,
      "risk_adj_lower_95": 0.001573166868327397,
      "risk_adj_upper_95": 0.03143057301048178,
      "drivers": [
        "zone-attributed confirmed count 1 for this source zone",
        "visibility-adjustment factor 2.04\u00d7 reflects under-reporting in source zone; raw risk likely understates true hazard"
      ]
    },
    {
      "source": "aru",
      "target": "kampala-uga",
      "horizon_days": 30,
      "risk_raw_lower_50": 0.002766600546920711,
      "risk_raw_upper_50": 0.007771468957515543,
      "risk_adj_lower_50": 0.005628163379674617,
      "risk_adj_upper_50": 0.015768600027865287,
      "risk_adj_lower_95": 0.001019947024902085,
      "risk_adj_upper_95": 0.03162338472298525,
      "drivers": [
        "zone-attributed confirmed count 1 for this source zone",
        "visibility-adjustment factor 2.04\u00d7 reflects under-reporting in source zone; raw risk likely understates true hazard"
      ]
    },
    {
      "source": "kilo",
      "target": "goma-cod",
      "horizon_days": 30,
      "risk_raw_lower_50": 0.0028451331002534164,
      "risk_raw_upper_50": 0.007770951095989936,
      "risk_adj_lower_50": 0.005787687967104743,
      "risk_adj_upper_50": 0.015767553555728592,
      "risk_adj_lower_95": 0.0018146509499915393,
      "risk_adj_upper_95": 0.03021339583169172,
      "drivers": [
        "zone-attributed confirmed count 1 for this source zone",
        "visibility-adjustment factor 2.04\u00d7 reflects under-reporting in source zone; raw risk likely understates true hazard"
      ]
    },
    {
      "source": "kilo",
      "target": "bundibugyo-uga",
      "horizon_days": 30,
      "risk_raw_lower_50": 0.0028593296462851303,
      "risk_raw_upper_50": 0.0077517741749349445,
      "risk_adj_lower_50": 0.0058165243288023916,
      "risk_adj_upper_50": 0.015728799951558903,
      "risk_adj_lower_95": 0.0018331055949618758,
      "risk_adj_upper_95": 0.03307457556142695,
      "drivers": [
        "zone-attributed confirmed count 1 for this source zone",
        "visibility-adjustment factor 2.04\u00d7 reflects under-reporting in source zone; raw risk likely understates true hazard"
      ]
    },
    {
      "source": "kilo",
      "target": "kampala-uga",
      "horizon_days": 30,
      "risk_raw_lower_50": 0.0029478532405849134,
      "risk_raw_upper_50": 0.007731467533447112,
      "risk_adj_lower_50": 0.0059963255471822685,
      "risk_adj_upper_50": 0.015687762357368823,
      "risk_adj_lower_95": 0.001343803060440324,
      "risk_adj_upper_95": 0.03689784418478586,
      "drivers": [
        "zone-attributed confirmed count 1 for this source zone",
        "visibility-adjustment factor 2.04\u00d7 reflects under-reporting in source zone; raw risk likely understates true hazard"
      ]
    },
    {
      "source": "kilo",
      "target": "kasese-uga",
      "horizon_days": 30,
      "risk_raw_lower_50": 0.0027101548771281403,
      "risk_raw_upper_50": 0.007669150266024327,
      "risk_adj_lower_50": 0.005513496193608802,
      "risk_adj_upper_50": 0.01556182061457037,
      "risk_adj_lower_95": 0.0013441882451480786,
      "risk_adj_upper_95": 0.03516910622856802,
      "drivers": [
        "zone-attributed confirmed count 1 for this source zone",
        "visibility-adjustment factor 2.04\u00d7 reflects under-reporting in source zone; raw risk likely understates true hazard"
      ]
    },
    {
      "source": "goma-cod",
      "target": "kasese-uga",
      "horizon_days": 30,
      "risk_raw_lower_50": 0.002865993846001197,
      "risk_raw_upper_50": 0.007644492687024107,
      "risk_adj_lower_50": 0.005830060650841379,
      "risk_adj_upper_50": 0.01551198575771437,
      "risk_adj_lower_95": 0.001573611409081327,
      "risk_adj_upper_95": 0.03145934487007516,
      "drivers": [
        "zone-attributed confirmed count 1 for this source zone",
        "visibility-adjustment factor 2.04\u00d7 reflects under-reporting in source zone; raw risk likely understates true hazard"
      ]
    },
    {
      "source": "goma-cod",
      "target": "beni-cod",
      "horizon_days": 30,
      "risk_raw_lower_50": 0.002744529108104965,
      "risk_raw_upper_50": 0.007583767978108613,
      "risk_adj_lower_50": 0.005583326818806994,
      "risk_adj_upper_50": 0.015389250994892023,
      "risk_adj_lower_95": 0.001269669502803647,
      "risk_adj_upper_95": 0.028043776897154673,
      "drivers": [
        "zone-attributed confirmed count 1 for this source zone",
        "visibility-adjustment factor 2.04\u00d7 reflects under-reporting in source zone; raw risk likely understates true hazard"
      ]
    }
  ],
  "analysis_dependency_audit": [
    {
      "surface": "public_reporting_trajectory",
      "status": "updated",
      "inputs": {
        "confirmed": 282,
        "suspected_active": 321,
        "suspected_cumulative": 3491,
        "deaths_confirmed": 43,
        "deaths_suspected": 246
      },
      "clock_basis": "ECDC 27 May confirmed/suspected counts carry a May 26 data/report date (attributed to DRC MoH on 26 May); INRB build-2026-05-28 cross-corroborates DRC-only cases and supplies the headline DRC death primary on the same data date. Confirmed deaths and suspected deaths are reconciled as two independent series matching the INRB-published schema; the prior cross-class composition is retired."
    },
    {
      "surface": "visibility_module_c",
      "status": "updated",
      "inputs": {
        "confirmed": 282,
        "suspected_cumulative": 3491
      },
      "outputs": {
        "reporting_completeness_50": [
          0.49085836786842113,
          0.5712706336969902
        ],
        "confirmation_backlog_50": [
          0,
          0
        ]
      },
      "clock_basis": "Snapshot-level visibility nowcast; prior-weighted with a Beta-Binomial update from the current confirmed/suspected headline pair."
    },
    {
      "surface": "confirmable_underlying_trajectory",
      "status": "updated",
      "inputs": {
        "confirmed_endpoint": 282,
        "reporting_completeness_50": [
          0.49085836786842113,
          0.5712706336969902
        ]
      },
      "outputs": {
        "endpoint_confirmable_50": [
          494,
          575
        ]
      },
      "clock_basis": "Confirmed endpoint is dated May 26 (DRC MoH per ECDC + INRB); the completeness posterior is the current snapshot posterior applied across the displayed confirmed-case series."
    },
    {
      "surface": "death_back_projection_and_grid",
      "status": "updated_snapshot_level",
      "inputs": {
        "deaths_confirmed": 43,
        "deaths_suspected": 246
      },
      "clock_basis": "Deaths-back-projection now consumes two independent dated series: deaths_confirmed (lab-confirmed only, the apples-to-apples denominator for CFR work) and deaths_suspected (the broader under-investigation total, the upper bound for outbreak-size estimation). ECDC's 238 DRC suspected deaths, CDC 25 May (223), the DRC MoH dashboard aggregate (179, 24 May), and the earlier ECDC 25 May figure (119) are held as dated conflict anchors against the suspected series."
    },
    {
      "surface": "transmission_depth",
      "status": "updated",
      "inputs": {
        "confirmed": 282
      },
      "clock_basis": "Transmission plausibility uses the current reconciled confirmed headline count."
    },
    {
      "surface": "corridor_watchlist",
      "status": "source_attribution_lag",
      "inputs": {
        "zone_attributed_confirmed": 109,
        "headline_confirmed": 282,
        "unallocated_headline_confirmed": 173
      },
      "blocked_by": "No reviewed May 26 cumulative health-zone table. The DRC MoH SitRep 009 dashboard rows and the INRB build-2026-05-28 bb8b7d5 processed health-zone layers (latest at 2026-05-26) remain source-review until their cumulative-table semantics and source labels are reviewed against original MoH/INSP publication context."
    }
  ],
  "mode_b_hypotheses": [
    {
      "hypothesis_id": "calibration-point:bdbv-uga-cod-2026:30d:e77003de63",
      "corridor": "bunia -> kampala-uga",
      "risk_adj_50": [
        0.229,
        0.523
      ],
      "block_id": "calibration-block:bdbv-uga-cod-2026:2026-05-20",
      "pinned_at": "2026-05-20",
      "resolves_at": "2026-06-19T23:59:59Z",
      "horizon_days": 30
    },
    {
      "hypothesis_id": "calibration-point:bdbv-uga-cod-2026:30d:bede8179ea",
      "corridor": "rwampara -> bundibugyo-uga",
      "risk_adj_50": [
        0.227,
        0.523
      ],
      "block_id": "calibration-block:bdbv-uga-cod-2026:2026-05-20",
      "pinned_at": "2026-05-20",
      "resolves_at": "2026-06-19T23:59:59Z",
      "horizon_days": 30
    },
    {
      "hypothesis_id": "calibration-point:bdbv-uga-cod-2026:30d:d853267eed",
      "corridor": "mongbwalu -> beni-cod",
      "risk_adj_50": [
        0.218,
        0.522
      ],
      "block_id": "calibration-block:bdbv-uga-cod-2026:2026-05-20",
      "pinned_at": "2026-05-20",
      "resolves_at": "2026-06-19T23:59:59Z",
      "horizon_days": 30
    },
    {
      "hypothesis_id": "calibration-point:bdbv-uga-cod-2026:30d:cf92d9f82b",
      "corridor": "rwampara -> kasese-uga",
      "risk_adj_50": [
        0.209,
        0.515
      ],
      "block_id": "calibration-block:bdbv-uga-cod-2026:2026-05-20",
      "pinned_at": "2026-05-20",
      "resolves_at": "2026-06-19T23:59:59Z",
      "horizon_days": 30
    },
    {
      "hypothesis_id": "calibration-point:bdbv-uga-cod-2026:30d:b4a76ed77f",
      "corridor": "bunia -> kasese-uga",
      "risk_adj_50": [
        0.22,
        0.553
      ],
      "block_id": "calibration-block:bdbv-uga-cod-2026:2026-05-21",
      "pinned_at": "2026-05-21",
      "resolves_at": "2026-06-20T23:59:59Z",
      "horizon_days": 30,
      "selection_role": "relative-high cross-border watch corridor",
      "risk_tier": "relative_high",
      "geography_class": "cross_border",
      "control_role": "watchlist_high"
    },
    {
      "hypothesis_id": "calibration-point:bdbv-uga-cod-2026:30d:e3efe4dd95",
      "corridor": "bunia -> beni-cod",
      "risk_adj_50": [
        0.243,
        0.525
      ],
      "block_id": "calibration-block:bdbv-uga-cod-2026:2026-05-21",
      "pinned_at": "2026-05-21",
      "resolves_at": "2026-06-20T23:59:59Z",
      "horizon_days": 30,
      "selection_role": "relative-high in-country likely-positive control",
      "risk_tier": "relative_high",
      "geography_class": "in_country",
      "control_role": "likely_positive"
    },
    {
      "hypothesis_id": "calibration-point:bdbv-uga-cod-2026:30d:92b62f4c0c",
      "corridor": "rwampara -> kampala-uga",
      "risk_adj_50": [
        0.218,
        0.515
      ],
      "block_id": "calibration-block:bdbv-uga-cod-2026:2026-05-21",
      "pinned_at": "2026-05-21",
      "resolves_at": "2026-06-20T23:59:59Z",
      "horizon_days": 30,
      "selection_role": "mid-band cross-border imported-case positive control",
      "risk_tier": "relative_mid",
      "geography_class": "cross_border",
      "control_role": "likely_positive"
    },
    {
      "hypothesis_id": "calibration-point:bdbv-uga-cod-2026:30d:d8ee2a62a9",
      "corridor": "mongbwalu -> kasese-uga",
      "risk_adj_50": [
        0.236,
        0.519
      ],
      "block_id": "calibration-block:bdbv-uga-cod-2026:2026-05-21",
      "pinned_at": "2026-05-21",
      "resolves_at": "2026-06-20T23:59:59Z",
      "horizon_days": 30,
      "selection_role": "mid-band cross-border watch corridor",
      "risk_tier": "relative_mid",
      "geography_class": "cross_border",
      "control_role": "watchlist_mid"
    },
    {
      "hypothesis_id": "calibration-point:bdbv-uga-cod-2026:30d:f3f474294b",
      "corridor": "rwampara -> beni-cod",
      "risk_adj_50": [
        0.236,
        0.518
      ],
      "block_id": "calibration-block:bdbv-uga-cod-2026:2026-05-21",
      "pinned_at": "2026-05-21",
      "resolves_at": "2026-06-20T23:59:59Z",
      "horizon_days": 30,
      "selection_role": "mid-band in-country likely-positive control",
      "risk_tier": "relative_mid",
      "geography_class": "in_country",
      "control_role": "likely_positive"
    },
    {
      "hypothesis_id": "calibration-point:bdbv-uga-cod-2026:30d:deb53c5269",
      "corridor": "bunia -> arua-uga",
      "risk_adj_50": [
        0.236,
        0.52
      ],
      "block_id": "calibration-block:bdbv-uga-cod-2026:2026-05-21",
      "pinned_at": "2026-05-21",
      "resolves_at": "2026-06-20T23:59:59Z",
      "horizon_days": 30,
      "selection_role": "mid-band cross-border blindspot watch corridor",
      "risk_tier": "relative_mid",
      "geography_class": "cross_border",
      "control_role": "blindspot_watch"
    },
    {
      "hypothesis_id": "calibration-point:bdbv-uga-cod-2026:30d:db608ab7c7",
      "corridor": "rwampara -> arua-uga",
      "risk_adj_50": [
        0.221,
        0.494
      ],
      "block_id": "calibration-block:bdbv-uga-cod-2026:2026-05-21",
      "pinned_at": "2026-05-21",
      "resolves_at": "2026-06-20T23:59:59Z",
      "horizon_days": 30,
      "selection_role": "relative-low cross-border likely-negative control",
      "risk_tier": "relative_low",
      "geography_class": "cross_border",
      "control_role": "likely_negative"
    },
    {
      "hypothesis_id": "calibration-point:bdbv-uga-cod-2026:30d:7da36f72ef",
      "corridor": "mongbwalu -> nebbi-uga",
      "risk_adj_50": [
        0.222,
        0.51
      ],
      "block_id": "calibration-block:bdbv-uga-cod-2026:2026-05-21",
      "pinned_at": "2026-05-21",
      "resolves_at": "2026-06-20T23:59:59Z",
      "horizon_days": 30,
      "selection_role": "relative-low cross-border likely-negative control",
      "risk_tier": "relative_low",
      "geography_class": "cross_border",
      "control_role": "likely_negative"
    },
    {
      "hypothesis_id": "calibration-point:bdbv-uga-cod-2026:30d:269808f993",
      "corridor": "bunia -> goma-cod",
      "risk_adj_50": [
        0.1024,
        0.2669
      ],
      "block_id": "calibration-block:bdbv-uga-cod-2026:2026-05-26",
      "pinned_at": "2026-05-26",
      "resolves_at": "2026-06-25T23:59:59Z",
      "horizon_days": 30,
      "selection_role": "Ituri-source -> Goma graduation pin (Ituri provincial capital)",
      "risk_tier": "relative_mid",
      "geography_class": "in_country",
      "control_role": "watchlist_mid"
    },
    {
      "hypothesis_id": "calibration-point:bdbv-uga-cod-2026:30d:d057737062",
      "corridor": "rwampara -> goma-cod",
      "risk_adj_50": [
        0.2034,
        0.4589
      ],
      "block_id": "calibration-block:bdbv-uga-cod-2026:2026-05-26",
      "pinned_at": "2026-05-26",
      "resolves_at": "2026-06-25T23:59:59Z",
      "horizon_days": 30,
      "selection_role": "Ituri-source -> Goma graduation pin (largest Ituri source zone by case count)",
      "risk_tier": "relative_high",
      "geography_class": "in_country",
      "control_role": "watchlist_high"
    },
    {
      "hypothesis_id": "calibration-point:bdbv-uga-cod-2026:30d:f4e8a4499d",
      "corridor": "mongbwalu -> goma-cod",
      "risk_adj_50": [
        0.0955,
        0.2518
      ],
      "block_id": "calibration-block:bdbv-uga-cod-2026:2026-05-26",
      "pinned_at": "2026-05-26",
      "resolves_at": "2026-06-25T23:59:59Z",
      "horizon_days": 30,
      "selection_role": "Ituri-source -> Goma graduation pin (Ituri mining-area source zone)",
      "risk_tier": "relative_mid",
      "geography_class": "in_country",
      "control_role": "watchlist_mid"
    }
  ],
  "calibration_clock": {
    "block_id": "calibration-block:bdbv-uga-cod-2026:2026-05-20",
    "status": "carried_forward",
    "point_count": 4,
    "hypothesis_ids": [
      "calibration-point:bdbv-uga-cod-2026:30d:e77003de63",
      "calibration-point:bdbv-uga-cod-2026:30d:bede8179ea",
      "calibration-point:bdbv-uga-cod-2026:30d:d853267eed",
      "calibration-point:bdbv-uga-cod-2026:30d:cf92d9f82b"
    ],
    "pinned_at": "2026-05-20",
    "as_of": "2026-05-31T23:59:59Z",
    "resolves_at": "2026-06-19T23:59:59Z",
    "horizon_days": 30,
    "elapsed_days": 11,
    "remaining_days": 19,
    "equation": "remaining_days = date(resolves_at) - date(as_of)"
  },
  "calibration_blocks": [
    {
      "block_id": "calibration-block:bdbv-uga-cod-2026:2026-05-20",
      "status": "carried_forward",
      "point_count": 4,
      "hypothesis_ids": [
        "calibration-point:bdbv-uga-cod-2026:30d:e77003de63",
        "calibration-point:bdbv-uga-cod-2026:30d:bede8179ea",
        "calibration-point:bdbv-uga-cod-2026:30d:d853267eed",
        "calibration-point:bdbv-uga-cod-2026:30d:cf92d9f82b"
      ],
      "pinned_at": "2026-05-20",
      "as_of": "2026-05-31T23:59:59Z",
      "resolves_at": "2026-06-19T23:59:59Z",
      "horizon_days": 30,
      "elapsed_days": 11,
      "remaining_days": 19,
      "equation": "remaining_days = date(resolves_at) - date(as_of)"
    },
    {
      "block_id": "calibration-block:bdbv-uga-cod-2026:2026-05-21",
      "status": "carried_forward",
      "point_count": 8,
      "hypothesis_ids": [
        "calibration-point:bdbv-uga-cod-2026:30d:b4a76ed77f",
        "calibration-point:bdbv-uga-cod-2026:30d:e3efe4dd95",
        "calibration-point:bdbv-uga-cod-2026:30d:92b62f4c0c",
        "calibration-point:bdbv-uga-cod-2026:30d:d8ee2a62a9",
        "calibration-point:bdbv-uga-cod-2026:30d:f3f474294b",
        "calibration-point:bdbv-uga-cod-2026:30d:deb53c5269",
        "calibration-point:bdbv-uga-cod-2026:30d:db608ab7c7",
        "calibration-point:bdbv-uga-cod-2026:30d:7da36f72ef"
      ],
      "pinned_at": "2026-05-21",
      "as_of": "2026-05-31T23:59:59Z",
      "resolves_at": "2026-06-20T23:59:59Z",
      "horizon_days": 30,
      "elapsed_days": 10,
      "remaining_days": 20,
      "equation": "remaining_days = date(resolves_at) - date(as_of)"
    },
    {
      "block_id": "calibration-block:bdbv-uga-cod-2026:2026-05-26",
      "status": "carried_forward",
      "point_count": 3,
      "hypothesis_ids": [
        "calibration-point:bdbv-uga-cod-2026:30d:269808f993",
        "calibration-point:bdbv-uga-cod-2026:30d:d057737062",
        "calibration-point:bdbv-uga-cod-2026:30d:f4e8a4499d"
      ],
      "pinned_at": "2026-05-26",
      "as_of": "2026-05-31T23:59:59Z",
      "resolves_at": "2026-06-25T23:59:59Z",
      "horizon_days": 30,
      "elapsed_days": 5,
      "remaining_days": 25,
      "equation": "remaining_days = date(resolves_at) - date(as_of)"
    }
  ],
  "scope_id": "epi:bdbv-uga-cod-2026",
  "resolves_at": "2026-06-19T23:59:59Z",
  "revision_note": "Snapshot is published 2026-05-28 over the 26 May data date and supersedes the 26 May snapshot (forward-dated method evolution under painting/immutability, not an in-place re-cut). The new surveillance inputs are the ECDC 27 May page (citing 'On 26 May, the Ministry of Health in DRC reported a total of 121 confirmed cases (including 17 deaths) and 1 077 suspected cases (including 238 deaths) in Ituri, North Kivu, and South Kivu provinces. Uganda has reported seven confirmed cases, including one death.') and the INRB build-2026-05-28 GitHub release (DRC-only national_moh, data-as-of 26 May), both byte-archived/hash-recorded. The promoted endpoints are 1077 suspected DRC cases, 128 total confirmed (121 DRC + 7 Uganda), 247 country-scope deaths (246 DRC suspected deaths from INRB/INSP + one Uganda confirmed death from ECDC/CDC), and 17 confirmed DRC deaths. These are the highest valid primaries on the latest date with explicit composition disclosure. The CDC 25 May page (906 suspected, 112 confirmed, 223 suspected deaths) and the ECDC 25 May page (101 confirmed, 904 suspected, 119 suspected deaths) drop to dated conflict anchors. CDC and WHO AFRO have not yet published an edition that catches up to the DRC MoH 26 May release. ECDC's 238 DRC suspected-death figure is retained as a same-day conflict anchor below INRB/INSP's 246. SitRep 009 and the DRC MoH dashboard rows remain source-review (no dateRapportage, no official PDF at capture). The corridor source-load is re-based (2026-05-28, forward-only) onto the INRB-UMIE/INSP per-health-zone series (by_lovs_zone): 18 monitored health zones carrying 109 zone-attributed confirmed cases (11 with confirmed cases), superseding the earlier SitRep-007 CDC/INSP hybrid. The unified confirmed cascade is 128 country-scope -> 121 DRC INSP-attributable national -> 109 zone-attributed + 12 DRC unallocated residual; the remaining 128-121=7 is the cross-border attribution lag (Uganda cases not in the DRC national series). Candidate target zones include arua-uga and nebbi-uga to close the documented Mahagi/Goli<->Arua cross-border blindspot. Pre-committed calibration points are carried forward UNCHANGED from data/calibration-ledger.json; no pin was re-derived. Mobility and confirmation-latency leverages are held as situational inputs (run_local) and are not injected into this provenance-strict public snapshot. See data/external_sources/.",
  "data_scale_used": "mixed_with_metric_floor",
  "attribution_lag_disclosure": {
    "per_metric": [
      {
        "metric": "confirmed",
        "timeliness": "near_timely",
        "share_attributed_to_zones": 0.9008
      },
      {
        "metric": "suspected",
        "timeliness": "timely",
        "share_attributed_to_zones": 0.9824
      },
      {
        "metric": "confirmed_deaths",
        "timeliness": "trailing",
        "share_attributed_to_zones": 0.2941
      },
      {
        "metric": "suspected_deaths",
        "timeliness": "timely",
        "share_attributed_to_zones": 0.9959
      }
    ],
    "narrative": "Confirmed deaths trail the national rollup by 1-3 weeks while the INRB clinical review queue catches up; confirmed and suspected case attribution are near-timely to timely respectively."
  },
  "insp_per_zone_block": {
    "as_of_data_date": "2026-05-26",
    "source_id": "inrb-umie-ebola-drc-2026-build-2026-05-28-bb8b7d5",
    "method_basis": "INRB_UMIE_INSP_per_zone_v1",
    "by_lovs_zone": {
      "aru": {
        "confirmed": 1,
        "suspected": 4,
        "confirmed_deaths": 0,
        "suspected_deaths": 1,
        "inrb_collapsed_from": [],
        "present_in_insp_classification": "present_with_data"
      },
      "bambu": {
        "confirmed": 0,
        "suspected": 10,
        "confirmed_deaths": 0,
        "suspected_deaths": 2,
        "inrb_collapsed_from": [],
        "present_in_insp_classification": "present_with_data"
      },
      "bunia": {
        "confirmed": 36,
        "suspected": 279,
        "confirmed_deaths": 2,
        "suspected_deaths": 55,
        "inrb_collapsed_from": [],
        "present_in_insp_classification": "present_with_data"
      },
      "butembo": {
        "confirmed": 3,
        "suspected": 10,
        "confirmed_deaths": 0,
        "suspected_deaths": 0,
        "inrb_collapsed_from": [],
        "present_in_insp_classification": "present_with_data"
      },
      "damas": {
        "confirmed": 0,
        "suspected": 4,
        "confirmed_deaths": 0,
        "suspected_deaths": 2,
        "inrb_collapsed_from": [],
        "present_in_insp_classification": "present_with_data"
      },
      "goma-cod": {
        "confirmed": 1,
        "suspected": 0,
        "confirmed_deaths": 0,
        "suspected_deaths": 0,
        "inrb_collapsed_from": [],
        "present_in_insp_classification": "present_with_data"
      },
      "karisimbi-cod": {
        "confirmed": 0,
        "suspected": 5,
        "confirmed_deaths": 0,
        "suspected_deaths": 0,
        "inrb_collapsed_from": [],
        "present_in_insp_classification": "present_with_data",
        "sibling_hz_cluster": "goma-greater"
      },
      "katwa": {
        "confirmed": 0,
        "suspected": 0,
        "confirmed_deaths": 0,
        "suspected_deaths": 0,
        "inrb_collapsed_from": [],
        "present_in_insp_classification": "present_but_zero"
      },
      "kilo": {
        "confirmed": 1,
        "suspected": 18,
        "confirmed_deaths": 0,
        "suspected_deaths": 0,
        "inrb_collapsed_from": [],
        "present_in_insp_classification": "present_with_data"
      },
      "komanda": {
        "confirmed": 0,
        "suspected": 0,
        "confirmed_deaths": 1,
        "suspected_deaths": 0,
        "inrb_collapsed_from": [],
        "present_in_insp_classification": "present_with_data"
      },
      "mambasa": {
        "confirmed": 0,
        "suspected": 5,
        "confirmed_deaths": 0,
        "suspected_deaths": 1,
        "inrb_collapsed_from": [],
        "present_in_insp_classification": "present_with_data"
      },
      "miti-murhesa": {
        "confirmed": 1,
        "suspected": 1,
        "confirmed_deaths": 0,
        "suspected_deaths": 0,
        "inrb_collapsed_from": [],
        "present_in_insp_classification": "present_with_data"
      },
      "mongbwalu": {
        "confirmed": 20,
        "suspected": 375,
        "confirmed_deaths": 0,
        "suspected_deaths": 88,
        "inrb_collapsed_from": [],
        "present_in_insp_classification": "present_with_data"
      },
      "nizi": {
        "confirmed": 2,
        "suspected": 15,
        "confirmed_deaths": 0,
        "suspected_deaths": 2,
        "inrb_collapsed_from": [],
        "present_in_insp_classification": "present_with_data"
      },
      "nyankunde": {
        "confirmed": 10,
        "suspected": 70,
        "confirmed_deaths": 0,
        "suspected_deaths": 15,
        "inrb_collapsed_from": [
          "Nyankunde"
        ],
        "present_in_insp_classification": "present_with_data"
      },
      "oicha": {
        "confirmed": 1,
        "suspected": 8,
        "confirmed_deaths": 0,
        "suspected_deaths": 0,
        "inrb_collapsed_from": [],
        "present_in_insp_classification": "present_with_data"
      },
      "rimba": {
        "confirmed": 0,
        "suspected": 14,
        "confirmed_deaths": 0,
        "suspected_deaths": 4,
        "inrb_collapsed_from": [],
        "present_in_insp_classification": "present_with_data"
      },
      "rwampara": {
        "confirmed": 33,
        "suspected": 240,
        "confirmed_deaths": 2,
        "suspected_deaths": 75,
        "inrb_collapsed_from": [],
        "present_in_insp_classification": "present_with_data"
      }
    },
    "national_at_data_date": {
      "confirmed": 121,
      "suspected": 1077,
      "confirmed_deaths": 17,
      "suspected_deaths": 246
    },
    "unallocated_residual": {
      "confirmed": 12,
      "suspected": 19,
      "confirmed_deaths": 12,
      "suspected_deaths": 1
    },
    "coverage_audit": {
      "present_with_data": [
        "aru",
        "bambu",
        "bunia",
        "butembo",
        "damas",
        "goma-cod",
        "karisimbi-cod",
        "kilo",
        "komanda",
        "mambasa",
        "miti-murhesa",
        "mongbwalu",
        "nizi",
        "nyankunde",
        "oicha",
        "rimba",
        "rwampara"
      ],
      "present_but_zero": [
        "katwa"
      ],
      "structurally_absent": []
    },
    "upstream_reference": {
      "publisher": "INRB-UMIE consortium",
      "data_publisher": "INSP DRC",
      "repository": "https://github.com/INRB-UMIE/Ebola_DRC_2026",
      "build": "build-2026-05-28-bb8b7d5",
      "data_as_of": "2026-05-26",
      "terms": "Per-health-zone series is INSP SitRep material; reuse with attribution to INSP and citation of the report number and date; confirm distribution terms with INSP before external republication."
    }
  },
  "per_zone_under_ascertainment_bands": {
    "method_basis": "africa_cdc_pcr_capacity_modulated_v1",
    "surface_role": "shadow_in_v1",
    "species_default_band": {
      "lo": 0.3,
      "hi": 0.9
    },
    "by_lovs_zone": {
      "aru": {
        "lo": 0.5988023952095808,
        "hi": 0.9
      },
      "bambu": {
        "lo": null,
        "hi": null
      },
      "bunia": {
        "lo": 0.5682894487592347,
        "hi": 0.9
      },
      "butembo": {
        "lo": 0.5970149253731344,
        "hi": 0.9
      },
      "damas": {
        "lo": null,
        "hi": null
      },
      "goma-cod": {
        "lo": null,
        "hi": null
      },
      "karisimbi-cod": {
        "lo": null,
        "hi": null
      },
      "katwa": {
        "lo": null,
        "hi": null
      },
      "kilo": {
        "lo": null,
        "hi": null
      },
      "komanda": {
        "lo": null,
        "hi": null
      },
      "mambasa": {
        "lo": null,
        "hi": null
      },
      "miti-murhesa": {
        "lo": null,
        "hi": null
      },
      "mongbwalu": {
        "lo": 0.5052631578947369,
        "hi": 0.9
      },
      "nizi": {
        "lo": null,
        "hi": null
      },
      "nyankunde": {
        "lo": 0.5797101449275363,
        "hi": 0.9
      },
      "oicha": {
        "lo": null,
        "hi": null
      },
      "rimba": {
        "lo": 0.5836575875486381,
        "hi": 0.9
      },
      "rwampara": {
        "lo": null,
        "hi": null
      }
    },
    "coverage_stats": {
      "modulated_zones": 6,
      "species_default_fallback_zones": 12,
      "total_zones": 18
    }
  }
}